Workbook
Name ListaInsumos: 'Registro de Insumos'!$D$18:$D$1993
Name SíntesePrecificação: 'Síntese de Precificação'!$B$7:$J$333
Name ListaInsumos: 'Precificação Produto | Custo Co'!$D$104:$D$1993
Name ListaInsumos: 'Precificação Serviços | Custo D'!$D$19:$D$1993
Name ListaInsumos: 'Base de Salários'!$D$18:$D$1989
Name ListaInsumos: 'Precificação Produto | Custo De'!$D$19:$D$1993

Sheet Menu
B2: Precificação
B9: KL Engenharia

Sheet Gastos Fixos
C1: Gastos Fixos
C9: Item | D9: Valor | G9: Faturamento Estimado | H9: =9378337.24 + 722090.73 -> 10100428
G10: Soma das Despesas | H10: =SUMIF(D14:D1248,"<>",E14:E1248) -> 2028424
D11: =IFERROR(IF(COUNTIF(teste!$A$7:$D1248,D10)>=1,"-","--"),"") -> -- | E11: =IFERROR(IF(COUNTIF(teste!$A$7:$D1248,H10)>=1,"-","--"),"") -> -- | F11: =IFERROR(IF(COUNTIF(teste!$A$7:$D1248,I10)>=1,"-","--"),"") -> -- | G11: % Fixos vs Faturamento | H11: =H10/H9 -> 0.20082555
C13: ID | D13: Item | E13: Valor
C14: 1 | D14: Despesas Administrativas | E14: 1461373.8
C15: 2 | D15: Despesas Financeiras | E15: 4468.34
C16: 3 | D16: Outras Despesas Operacionais | E16: 562581.93

Sheet Manual de Uso
B1: Manual de Uso
B7: Obs 1: | C7: Para melhor visualização da planilha de ferramenta estratégica, é recomendado que o tamanho da página ("zoom") seja ou 75% ou 90%. Para alterar isso, basta mudar no número que está depois do simbolo de impressão e antes do símbolo de cifrão.
B8: Obs 2: | C8: A página "Validação de Dados" é oculta, caso seja necessário mudanças, basta clicar nas três barrinhas no canto inferior esquerdo e selecionar a aba
B9: Obs 3: | C9: Para selecionar a data na página "Registro", basta clilcar duas vezes na célula e selecionar a data desejada
B10: Obs 4: | C10: Para registrar vários itens de uma vez só, basta escrever uma linha de registros e puxar para baixo
B11: Obs 5: | C11: Se o valor do item a ser registrado não for informado, o registro desse item não será feito
B12: Obs 6: | C12: O botão de apagar na aba "Registros" apaga os últimos itens registrados na aba "Base de Dados" e reescreve eles na aba "Registros"
B13: Obs 7: | C13: Sempre que for ADICIONAR/RETIRAR um item do plano de contas, lembrar que Adicionar/Retirar esse item da "Tabela de Validações" da aba de "Validações de Dados" (sem isso, esse item ainda irá aparecer no registro)
B14: Obs 8: | C14: NÃO deletar e nem adicionar colunas ou linhas, principalmente na aba de "Registros" e "Indicadores" - Essas alterações podem afetar o funcionamento da planilha. Se necessário, oculte linhas ou células
B15: Obs 9: | C15: Caso queiram buscar algum dado na "Base de Dados", basta clicar em "Ctrl + F" e digitar o valor que queira buscar ou usar os Filtros
B16: Obs 10: | C16: Na aba "Base de Dados", é possível filtrar as informações pela informação desejada, basta clicar no funil ao lado da informação desejada
B18: Trocar as instruções de acordo com o projeto, isso é só um template!!!

Sheet Gastos Variáveis
B1: Gastos Variáveis
C9: Taxa | D9: Porcentagem | G9: Soma das Porcentagens | H9: =SUMIF(D14:D1246,"<>",E14:E1246) -> 0.0094
D11: =IFERROR(IF(COUNTIF(teste!$A$7:$D1246,D10)>=1,"-","--"),"") -> -- | E11: =IFERROR(IF(COUNTIF(teste!$A$7:$D1246,H9)>=1,"-","--"),"") -> -- | F11: =IFERROR(IF(COUNTIF(teste!$A$7:$D1246,I10)>=1,"-","--"),"") -> --
C13: ID | D13: Item | E13: Valor
C14: 1 | D14: Impostos | E14: 0.0094

Sheet Registro de Insumos
D1: Registro de Insumos
A6: 0 | C6: SEERRO(FILTER( 'Base de Dados'!A7:Q; ('Base de Dados'!A7:A = C16) + (C16 = ""); ('Base de Dados'!E7:E = C17) + (C17 = ""); ('Base de Dados'!C7:C = C18) + (C18 = ""); ('Base de Dados'!I7:I = C19) + (C19 = ""); ('Base de Dados'!D7:D = C20) + (C20 = ""));) | D6: FILTER(A10:L14; (D10:D14 <> "") * (E10:E14 <> "") * (F10:F14 <> "") * (G10:G14 <> "") * (I10:I14 <> "") * (J10:J14 <> ""))
B8: Editar | C8: Registro | AD8: =COUNTA($U$11:$U$15) -> 1
B9: Registro | C9: Item | D9: Unidade de Medida | E9: Quantidade Referência | F9: Custo Referência | V9: ID | W9: Data | X9: Item | Y9: Fluxo | Z9: Tipo | AA9: Centro | AB9: Descrição | AC9: Forma de pagamento | AD9: Valor Total | AE9: Parcelas | AF9: Desconto
U10: =U11 -> #N/A | V10: =V11 | W10: =W11 | X10: =X11 | Y10: =Y11 | Z10: =Z11 | AA10: =AA11 | AB10: =AB11 | ... AF10: =AF11
U11: =IFERROR(__xludf.DUMMYFUNCTION("FILTER(A10:L14, (D10:D14 <> """") * (E10:E14 <> """") * (F10:F14 <> """") * (G10:G14 <> """"))"),"#N/A") -> #N/A
C17: ID | D17: Item | E17: Unidade | F17: Quantidade Ref | G17: Custo Ref
C18: 0 F202AC-40/0,03 | D18: DR 2P 40A.30MA ABB | E18: Unidade | F18: 1 | G18: 0
C19: 10289152 | D19: BORNE BTWP 16-AZ 750 V | E19: Unidade | F19: 1 | G19: 6.43
C20: 11898941 | D20: CHAVE SECCIONADORA ROTATIVA MSW 80A 3 POLOS COM MANOPLA VERMELHA / AMARELA PARA MONTAGEM EM BASE ATE | E20: Unidade | F20: 1 | G20: 221.75
C21: 12486844 | D21: MINICONTATOR AZ CWCA0-31-00V26 190V 50HZ/220V 60HZ AZUL | E21: Unidade | F21: 1 | G21: 32.55
C22: 12486847 | D22: MINICONTATOR AZ CWCA0-40-00V26 190V 50HZ/220V 60HZ AZUL | E22: Unidade | F22: 1 | G22: 32.55
C23: 12499384 | D23: BLOCO CONTATO AUXILIAR FRONTAL BFCA 3NA+1NF COM PARAFUSO UI MAX=660/690 VOLTS AZUL MINICONTATOR CWCA | E23: Unidade | F23: 1 | G23: 24.59
C24: 12499385 | D24: BLOCO CONTATO AUXILIAR FRONTAL BFCA 4NA COM PARAFUSO UI MAX=660/690 VOLTS AZUL MINICONTATOR CWCA0 | E24: Unidade | F24: 1 | G24: 24.59
C25: 12775000 | D25: BLOCO DE CONTATO BC-1R PARA DISJUNTOR CAIXA MOLDADA AGW50-250 | E25: Unidade | F25: 1 | G25: 53.4
C26: 12775002 | D26: BLOCO DE ALARME AL-1R PARA DISJUNTOR CAIXA MOLDADA AGW50-250 | E26: Unidade | F26: 1 | G26: 59.05
C27: 12775054 | D27: BOBINA DE DISPARO BD 110-220 VCA/VCC PARA DISJUNTOR CAIXA MOLDADA AGW400-800 | E27: Unidade | F27: 1 | G27: 174.65
C28: 12775103 | D28: DISJUNTOR EM CAIXA MOLDADA AGW250 30 KA (380 VCA) MAGNETICO E TERMICO FIXO 125 A 3 POLOS | E28: Unidade | F28: 1 | G28: 220.19
C29: 12775150 | D29: DISJUNTOR EM CAIXA MOLDADA AGW400 42 KA (380 VCA) MAGNETICO E TERMICO FIXO 350 A 3 POLOS | E29: Unidade | F29: 1 | G29: 699.22
C30: 12778357 | D30: MANOPLA ROTATIVA MR 469 MM CINZA PARA DISJUNTOR CAIXA MOLDADA AGW250 | E30: Unidade | F30: 1 | G30: 205.75
... C74: 7595 | D74: TECLADO S/FIO KIT + MOUSE S/FIO USB NANO REF. MK-295 LOGITECH | E74: Unidade | F74: 1 | G74: 269.9
C75: 01.05.10.0023 | D75: CH ALLEN T 6MM /SATA | E75: Unidade | F75: 1 | G75: 25.98
C76: 01.05.10.0024 | D76: CH ALLEN T 5MM /SATA | E76: Unidade | F76: 1 | G76: 20.83
C77: 10413668 | D77: CMS2-15 LUVA CRISTAL | E77: Unidade | F77: 1 | G77: 164.3
C78: 10415378 | D78: CMS2/3-18 LUVA CRISTAL | E78: Unidade | F78: 1 | G78: 0.77
C79: 110083 | D79: CADEADO LATAO 50MM PADO | E79: Unidade | F79: 1 | G79: 48
C80: 111764 | D80: SPRAY PINTURA 400ML AZUL MOTOR RADCOLOR | E80: Unidade | F80: 1 | G80: 17
C81: 112490 | D81: FITA DUPLA FACE TRANSP 19MM X 2M ADERMAX ADERE | E81: Unidade | F81: 1 | G81: 15
C82: 113549 | D82: PRIMER MANTA BASE DGUA 1LT PRODESIVO/WADIMEX | E82: Unidade | F82: 1 | G82: 15
C83: 113780 | D83: PINO JUNCAO MACHO 2P+T 10AMP PRETO/BRANCO TRAMONTI | E83: Unidade | F83: 1 | G83: 8.5
C84: 115458 | D84: MASSA PLASTICA BRANCA 400G IBERE | E84: Unidade | F84: 1 | G84: 19.5
C85: 115523 | D85: PARAF MITOFIX 4.5 X 40 BELENUS/CISER | E85: Unidade | F85: 1 | G85: 0.3
C86: 116079 | D86: PARAF ROSCA SOBERBA C/SEXT ZINC 1/4 X 60MM CISER | E86: Unidade | F86: 1 | G86: 0.9
C87: 116292 | D87: DISCO CORTE C/DEPRESSAO 9 X 1/8 X 7/8 CARBORUNDUM | E87: Unidade | F87: 1 | G87: 22
C88: 116322 | D88: FITA CREPE 48MM X 50M R-427 ADERE | E88: Unidade | F88: 1 | G88: 14
... C164: 601291 | D164: CADEADO PORTA DE ENROLAR TETRA 17500 DOVALE | E164: Unidade | F164: 1 | G164: 85
C165: 06012A80E2 | D165: LIXADEIRA DE PALMA GSS 140 A 220 W 220 V | E165: Unidade | F165: 1 | G165: 317.22
C166: 601305 | D166: PASSA FIO ALMA DE ACO 10 MT CORTAG | E166: Unidade | F166: 1 | G166: 27.5
C167: 601553 | D167: TRENA ACO C/TRAVA 3MT REF KTS12 STARRETT | E167: Unidade | F167: 1 | G167: 15
C168: 601758 | D168: ABRACADEIRA DE NYLON PRETA 4.8 X 200MM PARAMAX | E168: Unidade | F168: 1 | G168: 12
C169: 6036000752 | D169: FECHO LINGUETA COM DOBRA 2X45MM TRIANGULO PRETO | E169: Unidade | F169: 1 | G169: 0
C170: 6036001652 | D170: FECHO LINGUETA C/DOBRA 2X45MM C/ACIONADOR PRETO | E170: Unidade | F170: 1 | G170: 0
C171: 65 | D171: QDEPOB | E171: Unidade | F171: 1 | G171: 24
C172: 06506.6511.30 | D172: FECHADURA 6511 P/MOVEIS ACO 90 ROSCA TOTAL KA CROMADO | E172: Unidade | F172: 1 | G172: 8.07
C173: 06702.0305.13 | D173: LINGUETA FURO 8.4 C/DOBRA 1.5X49MM ZINCO BRANCO | E173: Unidade | F173: 1 | G173: 0.73
C174: 82469 | D174: PILHA ALCALINA AA RAYOVAC ( CARTELA COM 06 PILHAS ) | E174: Unidade | F174: 1 | G174: 22.9
C175: 82470 | D175: PILHA ALCALINA AAA ( PALITO ) RAYOVAC ( CARTELA COM 06 PILHAS ) | E175: Unidade | F175: 1 | G175: 22.9
C176: 85 | D176: QF-HIDRANTES | E176: Unidade | F176: 1 | G176: 24
C177: 93200228 | D177: BRPD01 - PORTA DOCUMENTOS A4 | E177: Unidade | F177: 1 | G177: 24.12
C178: 94200099 | D178: BRCE-120.80.25 - CAIXA P/PROT. DE COMANDO - IP66 - 1200X800X250 | E178: Unidade | F178: 1 | G178: 1326.15
C179: 94200100 | D179: BRCE-120.80.35 - CAIXA P/PROT. DE COMANDO - IP66 - 1200X800X350 | E179: Unidade | F179: 1 | G179: 1316.52
C180: 94200206 | D180: BRCE-100.80.30 - CAIXA P/PROT. DE COMANDO - IP66 - 1000X800X300 | E180: Unidade | F180: 1 | G180: 1119.37
C181: 94200087 | D181: CAIXA P/PROT.DE COMANDO 600X600X200 | E181: Unidade | F181: 1 | G181: 463.84
C182: 94200099 | D182: CAIXA P/PROT.DE COMANDO 1200X800X250 | E182: Unidade | F182: 1 | G182: 1259.84
C183: 0SH0118 | D183: SERRA COPO DE (29MM) | E183: Unidade | F183: 1 | G183: 0
C184: 1.1/2" | D184: COPEX METALICO 1.1/2 POL | E184: Unidade | F184: 1 | G184: 0
C185: 1.1/4" | D185: COPEX METALICO 1.1/4 POL | E185: Unidade | F185: 1 | G185: 0
C186: 1/4´´ | D186: BROCA P/FAZER ROSCA MACHO 1/4 | E186: Unidade | F186: 1 | G186: 19.05
C187: 10 | D187: CAIXA P/ MED. DE GAS 600X500X200 MM | E187: Unidade | F187: 1 | G187: 0
C188: 1000017181 | D188: CHAPA LISA 0.80X1200X3000MM ELETROGALV | E188: Unidade | F188: 1 | G188: 242.25
C189: 1000017193 | D189: CHAPA LISA 0.95X1200X3000MM ELETROGALV | E189: Unidade | F189: 1 | G189: 282.04
C190: 1000017206 | D190: CHAPA LISA 1.25X1200X3000MM BZ Z275 | E190: Unidade | F190: 1 | G190: 371.07
C191: 1000017222 | D191: CHAPA LISA 1.55X1200X3000MM BZ Z275 | E191: Unidade | F191: 1 | G191: 460.11
C192: 1000017224 | D192: CHAPA LISA 1.55X1200X3000MM ELETROGALV | E192: Unidade | F192: 1 | G192: 460.11
C193: 10004973 | D193: TINTA PO POLITHERM 20 MUNSELL 2.5YR 6/14 W LARANJA | E193: Unidade | F193: 1 | G193: 1078.8
C194: 10005576 | D194: TINTA PO POLITHERM 21 DIRETIVA ROHS PADRAO WEG W PRETO | E194: Unidade | F194: 1 | G194: 1069.3
C195: 100291 | D195: ARAME MIG ER70S-6 0.80MM 15KG | E195: Unidade | F195: 1 | G195: 17.7
C196: 10031 | D196: FITA CREPE 18MMX50M | E196: Unidade | F196: 1 | G196: 4.9
C197: 10057832 | D197: TINTA PO POLITHERM 26 DIRETIVA ROHS RAL 9003 W BRANCO | E197: Unidade | F197: 1 | G197: 1014.7
C198: 1006954 | D198: LUMINARIA LED SLIM 9W 6500K AP | E198: Unidade | F198: 1 | G198: 25.9
... C227: 10076465 | D227: DISJ. 3P 63A.3KA WEG | E227: Unidade | F227: 1 | G227: 64.4
C228: 101 FP 3X2.1/2 | D228: DOBRADICA DE 3X2.1/2 101FP | E228: Unidade | F228: 1 | G228: 0
C229: 101 FZL 2 | D229: DOBRADICA DE 2 101FZL | E229: Unidade | F229: 1 | G229: 0
C230: 1010200000 | D230: #CONECTOR WPE 6 VERDE | E230: Unidade | F230: 1 | G230: 11.3
C231: 1015 | D231: BRAC. COPO 01/2" GALV. | E231: Unidade | F231: 1 | G231: 2.47
C232: 10187575 | D232: DISJ. 3P C 200A.22KA WEG | E232: Unidade | F232: 1 | G232: 0
C233: 1020000000 | D233: #CONECTOR WDU 2.5 BEGE | E233: Unidade | F233: 1 | G233: 1.83
C234: 1020200000 | D234: #CONECTOR WDU 6 BEGE | E234: Unidade | F234: 1 | G234: 2.84
C235: 10261745 | D235: BORNE BTWP 6/10T-VD/AM WEG | E235: Unidade | F235: 1 | G235: 11.16
C236: 10289060 | D236: POSTE FINAL PF3-BTW PLASTICO 750V/600V (IEC/UL) | E236: Unidade | F236: 1 | G236: 1.36
C237: 10289148 | D237: BORNE BTWP 6-AZ 630 V | E237: Unidade | F237: 1 | G237: 3.58
C238: 1030 | D238: FUSIVEL DE 100A NH01 | E238: Unidade | F238: 1 | G238: 0
C239: 10358 | D239: PROTETOR AUDITIVO REUTILIZAVEL | E239: Unidade | F239: 1 | G239: 5.62
C240: 10409918 | D240: CONTATOR CWM 112A WEG | E240: Unidade | F240: 1 | G240: 0
C241: 10413820 | D241: SOFT-STARTER 10A WEG | E241: Unidade | F241: 1 | G241: 0
... C249: 1090000 | D249: ARMARIO COMPACTO AX 600X1000X250MM RAL7035 | E249: Unidade | F249: 1 | G249: 963.33
C250: 10X24 | D250: BROCA P/FAZER ROSCA MACHO 10X24 | E250: Unidade | F250: 1 | G250: 0
C251: 111 | D251: BARRAMENTO 1/2X1/8 | E251: Unidade | F251: 1 | G251: 0
C252: 1110 | D252: BARRAMENTO 1.1/2X1/4 | E252: Unidade | F252: 1 | G252: 512
C253: 1111 | D253: BARRAMENTO 1.1/4X1/4 | E253: Unidade | F253: 1 | G253: 80.6
C254: 1112 | D254: BARRAMENTO 1.1/2X1/8 | E254: Unidade | F254: 1 | G254: 0
C255: 1113 | D255: BARRAMENTO 3/4X1/4 | E255: Unidade | F255: 1 | G255: 80
C256: 11134791 | D256: DISJ. 3P 70A.3KA WEG | E256: Unidade | F256: 1 | G256: 66.13
C257: 1114 | D257: BARRAMENTO 2X3/8 | E257: Unidade | F257: 1 | G257: 1040
C258: 1114000 | D258: ARMARIO COMPACTO AX 1000X1400X300MM RAL7035 | E258: Unidade | F258: 1 | G258: 2871.19
C259: 1115 | D259: BARRAMENTO 2.1/2X1/4 | E259: Unidade | F259: 1 | G259: 0
C260: 1116 | D260: BARRAMENTO 2.1/2X3/8 | E260: Unidade | F260: 1 | G260: 86
C261: 1117 | D261: BARRAMENTO 2X3/16 | E261: Unidade | F261: 1 | G261: 0
C262: 1118 | D262: BARRAMENTO 2X1/4 | E262: Unidade | F262: 1 | G262: 0
... C366: 13 | D366: CAIXA ABRIGO P/ 06 MED. DE GAS EMBUTIR 1000X500X180 MM | E366: Unidade | F366: 1 | G366: 0
...

Sheet Painel de Visualização
B1: Painel de Visualização
B7: Data Inicial | C7: 45474 | L7: Ano e Mês | M7: Entrada | N7: Saída | O7: Lucro Líquido | P7: Fluxo de Caixa Acumulado | Q7: Custos Fixos | R7: Custos Variáveis | S7: Despesas | T7: Investimentos | U7: Inadimplência | V7: Runway | W7: Margem de Contribuição | X7: Breakeven | Y7: Margem Líquida | Z7: Faturamento | AD7: {=TRANSPOSE(B28:B554)} -> Ensaio de Casal | AE7: Ensaio simples | AF7: Ensaio de 15 anos | AG7: Ensaio de Formatura | AH7: Ensaio de Noivos
B8: Data Final | C8: 45627 | L8: =IFERROR(__xludf.DUMMYFUNCTION("FILTER(Indicadores!D27:R554,Indicadores!D27:D554>=C7,Indicadores!D27:D554<=C8)"),45474.0) -> 45474 | M8: =IFERROR(__xludf.DUMMYFUNCTION("""COMPUTED_VALUE"""),"#N/A") -> #N/A | N8: =IFERROR(__xludf.DUMMYFUNCTION("""COMPUTED_VALUE"""),"#N/A") -> #N/A | O8: =IFERROR(__xludf.DUMMYFUNCTION("""COMPUTED_VALUE"""),"#N/A") -> #N/A | P8: =IFERROR(__xludf.DUMMYFUNCTION("""COMPUTED_VALUE"""),"#N/A") -> #N/A | Q8: =IFERROR(__xludf.DUMMYFUNCTION("""COMPUTED_VALUE"""),"#N/A") -> #N/A | R8: =IFERROR(__xludf.DUMMYFUNCTION("""COMPUTED_VALUE"""),"#N/A") -> #N/A | S8: =IFERROR(__xludf.DUMMYFUNCTION("""COMPUTED_VALUE"""),"#N/A") -> #N/A | T8: =IFERROR(__xludf.DUMMYFUNCTION("""COMPUTED_VALUE"""),"#N/A") -> #N/A | U8: =IFERROR(__xludf.DUMMYFUNCTION("""COMPUTED_VALUE"""),"#N/A") -> #N/A | V8: =IFERROR(__xludf.DUMMYFUNCTION("""COMPUTED_VALUE"""),0.0) -> 0 | W8: =IFERROR(__xludf.DUMMYFUNCTION("""COMPUTED_VALUE"""),0.0) -> 0 | X8: =IFERROR(__xludf.DUMMYFUNCTION("""COMPUTED_VALUE"""),0.0) -> 0 | Y8: =IFERROR(__xludf.DUMMYFUNCTION("""COMPUTED_VALUE"""),0.0) -> 0 | Z8: =IFERROR(__xludf.DUMMYFUNCTION("""COMPUTED_VALUE"""),"#N/A") -> #N/A | AD8: =IFERROR(__xludf.DUMMYFUNCTION("FILTER('Base de Dados'!$M$7:$M554,'Base de Dados'!$B$7:$B554>=$C$7,'Base de Dados'!$B$7:$B554<=$C$8,'Base de Dados'!$D$7:$D554=AD$7,'Base de Dados'!$C$7:$C554=""Sim"")"),"#REF!") -> #REF! | AE8: =IFERROR(__xludf.DUMMYFUNCTION("FILTER('Base de Dados'!$M$7:$M554,'Base de Dados'!$B$7:$B554>=$C$7,'Base de Dados'!$B$7:$B554<=$C$8,'Base de Dados'!$D$7:$D554=AE$7,'Base de Dados'!$C$7:$C554=""Sim"")"),"#REF!") -> #REF! | AF8: =IFERROR(__xludf.DUMMYFUNCTION("FILTER('Base de Dados'!$M$7:$M554,'Base de Dados'!$B$7:$B554>=$C$7,'Base de Dados'!$B$7:$B554<=$C$8,'Base de Dados'!$D$7:$D554=AF$7,'Base de Dados'!$C$7:$C554=""Sim"")"),"#REF!") -> #REF! | AG8: =IFERROR(__xludf.DUMMYFUNCTION("FILTER('Base de Dados'!$M$7:$M554,'Base de Dados'!$B$7:$B554>=$C$7,'Base de Dados'!$B$7:$B554<=$C$8,'Base de Dados'!$D$7:$D554=AG$7,'Base de Dados'!$C$7:$C554=""Sim"")"),"#REF!") -> #REF! | AH8: =IFERROR(__xludf.DUMMYFUNCTION("FILTER('Base de Dados'!$M$7:$M554,'Base de Dados'!$B$7:$B554>=$C$7,'Base de Dados'!$B$7:$B554<=$C$8,'Base de Dados'!$D$7:$D554=AH$7,'Base de Dados'!$C$7:$C554=""Sim"")"),"#REF!") -> #REF!
L9: =IFERROR(__xludf.DUMMYFUNCTION("""COMPUTED_VALUE"""),45505.0) -> 45505 | M9: =IFERROR(__xludf.DUMMYFUNCTION("""COMPUTED_VALUE"""),"#N/A") -> #N/A | N9: =IFERROR(__xludf.DUMMYFUNCTION("""COMPUTED_VALUE"""),"#N/A") -> #N/A | O9: =IFERROR(__xludf.DUMMYFUNCTION("""COMPUTED_VALUE"""),"#N/A") -> #N/A | P9: =IFERROR(__xludf.DUMMYFUNCTION("""COMPUTED_VALUE"""),"#N/A") -> #N/A | Q9: =IFERROR(__xludf.DUMMYFUNCTION("""COMPUTED_VALUE"""),"#N/A") -> #N/A | R9: =IFERROR(__xludf.DUMMYFUNCTION("""COMPUTED_VALUE"""),"#N/A") -> #N/A | S9: =IFERROR(__xludf.DUMMYFUNCTION("""COMPUTED_VALUE"""),"#N/A") -> #N/A | T9: =IFERROR(__xludf.DUMMYFUNCTION("""COMPUTED_VALUE"""),"#N/A") -> #N/A | U9: =IFERROR(__xludf.DUMMYFUNCTION("""COMPUTED_VALUE"""),"#N/A") -> #N/A | V9: =IFERROR(__xludf.DUMMYFUNCTION("""COMPUTED_VALUE"""),0.0) -> 0 | W9: =IFERROR(__xludf.DUMMYFUNCTION("""COMPUTED_VALUE"""),0.0) -> 0 | X9: =IFERROR(__xludf.DUMMYFUNCTION("""COMPUTED_VALUE"""),0.0) -> 0 | Y9: =IFERROR(__xludf.DUMMYFUNCTION("""COMPUTED_VALUE"""),0.0) -> 0 | Z9: =IFERROR(__xludf.DUMMYFUNCTION("""COMPUTED_VALUE"""),"#N/A") -> #N/A
B10: Entradas Efetivas | L10: =IFERROR(__xludf.DUMMYFUNCTION("""COMPUTED_VALUE"""),45536.0) -> 45536 | M10: =IFERROR(__xludf.DUMMYFUNCTION("""COMPUTED_VALUE"""),"#N/A") -> #N/A | N10: =IFERROR(__xludf.DUMMYFUNCTION("""COMPUTED_VALUE"""),"#N/A") -> #N/A | O10: =IFERROR(__xludf.DUMMYFUNCTION("""COMPUTED_VALUE"""),"#N/A") -> #N/A | P10: =IFERROR(__xludf.DUMMYFUNCTION("""COMPUTED_VALUE"""),"#N/A") -> #N/A | Q10: =IFERROR(__xludf.DUMMYFUNCTION("""COMPUTED_VALUE"""),"#N/A") -> #N/A | R10: =IFERROR(__xludf.DUMMYFUNCTION("""COMPUTED_VALUE"""),"#N/A") -> #N/A | S10: =IFERROR(__xludf.DUMMYFUNCTION("""COMPUTED_VALUE"""),"#N/A") -> #N/A | T10: =IFERROR(__xludf.DUMMYFUNCTION("""COMPUTED_VALUE"""),"#N/A") -> #N/A | U10: =IFERROR(__xludf.DUMMYFUNCTION("""COMPUTED_VALUE"""),"#N/A") -> #N/A | V10: =IFERROR(__xludf.DUMMYFUNCTION("""COMPUTED_VALUE"""),0.0) -> 0 | W10: =IFERROR(__xludf.DUMMYFUNCTION("""COMPUTED_VALUE"""),0.0) -> 0 | X10: =IFERROR(__xludf.DUMMYFUNCTION("""COMPUTED_VALUE"""),0.0) -> 0 | Y10: =IFERROR(__xludf.DUMMYFUNCTION("""COMPUTED_VALUE"""),0.0) -> 0 | Z10: =IFERROR(__xludf.DUMMYFUNCTION("""COMPUTED_VALUE"""),"#N/A") -> #N/A
L11: =IFERROR(__xludf.DUMMYFUNCTION("""COMPUTED_VALUE"""),45566.0) -> 45566 | M11: =IFERROR(__xludf.DUMMYFUNCTION("""COMPUTED_VALUE"""),"#N/A") -> #N/A | N11: =IFERROR(__xludf.DUMMYFUNCTION("""COMPUTED_VALUE"""),"#N/A") -> #N/A | O11: =IFERROR(__xludf.DUMMYFUNCTION("""COMPUTED_VALUE"""),"#N/A") -> #N/A | P11: =IFERROR(__xludf.DUMMYFUNCTION("""COMPUTED_VALUE"""),"#N/A") -> #N/A | Q11: =IFERROR(__xludf.DUMMYFUNCTION("""COMPUTED_VALUE"""),"#N/A") -> #N/A | R11: =IFERROR(__xludf.DUMMYFUNCTION("""COMPUTED_VALUE"""),"#N/A") -> #N/A | S11: =IFERROR(__xludf.DUMMYFUNCTION("""COMPUTED_VALUE"""),"#N/A") -> #N/A | T11: =IFERROR(__xludf.DUMMYFUNCTION("""COMPUTED_VALUE"""),"#N/A") -> #N/A | U11: =IFERROR(__xludf.DUMMYFUNCTION("""COMPUTED_VALUE"""),"#N/A") -> #N/A | V11: =IFERROR(__xludf.DUMMYFUNCTION("""COMPUTED_VALUE"""),0.0) -> 0 | W11: =IFERROR(__xludf.DUMMYFUNCTION("""COMPUTED_VALUE"""),0.0) -> 0 | X11: =IFERROR(__xludf.DUMMYFUNCTION("""COMPUTED_VALUE"""),0.0) -> 0 | Y11: =IFERROR(__xludf.DUMMYFUNCTION("""COMPUTED_VALUE"""),0.0) -> 0 | Z11: =IFERROR(__xludf.DUMMYFUNCTION("""COMPUTED_VALUE"""),"#N/A") -> #N/A
B12: {=IF(C8>=C7,SUM(XLOOKUP(C7,Indicadores!$D$27:$D554,Indicadores!$E$27:$E554):XLOOKUP(C8,Indicadores!$D$27:$D554,Indicadores!$E$27:$E554)),"Insira uma Data Final maior ou igual à Data Inicial")} -> #N/A | E12: Custo Fixo | F12: Custo Variável | G12: Despesas | H12: Investimentos | I12: Inadimplência | L12: =IFERROR(__xludf.DUMMYFUNCTION("""COMPUTED_VALUE"""),45597.0) -> 45597 | M12: =IFERROR(__xludf.DUMMYFUNCTION("""COMPUTED_VALUE"""),"#N/A") -> #N/A | N12: =IFERROR(__xludf.DUMMYFUNCTION("""COMPUTED_VALUE"""),"#N/A") -> #N/A | O12: =IFERROR(__xludf.DUMMYFUNCTION("""COMPUTED_VALUE"""),"#N/A") -> #N/A | P12: =IFERROR(__xludf.DUMMYFUNCTION("""COMPUTED_VALUE"""),"#N/A") -> #N/A | Q12: =IFERROR(__xludf.DUMMYFUNCTION("""COMPUTED_VALUE"""),"#N/A") -> #N/A | R12: =IFERROR(__xludf.DUMMYFUNCTION("""COMPUTED_VALUE"""),"#N/A") -> #N/A | S12: =IFERROR(__xludf.DUMMYFUNCTION("""COMPUTED_VALUE"""),"#N/A") -> #N/A | T12: =IFERROR(__xludf.DUMMYFUNCTION("""COMPUTED_VALUE"""),"#N/A") -> #N/A | U12: =IFERROR(__xludf.DUMMYFUNCTION("""COMPUTED_VALUE"""),"#N/A") -> #N/A | V12: =IFERROR(__xludf.DUMMYFUNCTION("""COMPUTED_VALUE"""),0.0) -> 0 | W12: =IFERROR(__xludf.DUMMYFUNCTION("""COMPUTED_VALUE"""),0.0) -> 0 | X12: =IFERROR(__xludf.DUMMYFUNCTION("""COMPUTED_VALUE"""),0.0) -> 0 | Y12: =IFERROR(__xludf.DUMMYFUNCTION("""COMPUTED_VALUE"""),0.0) -> 0 | Z12: =IFERROR(__xludf.DUMMYFUNCTION("""COMPUTED_VALUE"""),"#N/A") -> #N/A
L13: =IFERROR(__xludf.DUMMYFUNCTION("""COMPUTED_VALUE"""),45627.0) -> 45627 | M13: =IFERROR(__xludf.DUMMYFUNCTION("""COMPUTED_VALUE"""),"#N/A") -> #N/A | N13: =IFERROR(__xludf.DUMMYFUNCTION("""COMPUTED_VALUE"""),"#N/A") -> #N/A | O13: =IFERROR(__xludf.DUMMYFUNCTION("""COMPUTED_VALUE"""),"#N/A") -> #N/A | P13: =IFERROR(__xludf.DUMMYFUNCTION("""COMPUTED_VALUE"""),"#N/A") -> #N/A | Q13: =IFERROR(__xludf.DUMMYFUNCTION("""COMPUTED_VALUE"""),"#N/A") -> #N/A | R13: =IFERROR(__xludf.DUMMYFUNCTION("""COMPUTED_VALUE"""),"#N/A") -> #N/A | S13: =IFERROR(__xludf.DUMMYFUNCTION("""COMPUTED_VALUE"""),"#N/A") -> #N/A | T13: =IFERROR(__xludf.DUMMYFUNCTION("""COMPUTED_VALUE"""),"#N/A") -> #N/A | U13: =IFERROR(__xludf.DUMMYFUNCTION("""COMPUTED_VALUE"""),"#N/A") -> #N/A | V13: =IFERROR(__xludf.DUMMYFUNCTION("""COMPUTED_VALUE"""),0.0) -> 0 | W13: =IFERROR(__xludf.DUMMYFUNCTION("""COMPUTED_VALUE"""),0.0) -> 0 | X13: =IFERROR(__xludf.DUMMYFUNCTION("""COMPUTED_VALUE"""),0.0) -> 0 | Y13: =IFERROR(__xludf.DUMMYFUNCTION("""COMPUTED_VALUE"""),0.0) -> 0 | Z13: =IFERROR(__xludf.DUMMYFUNCTION("""COMPUTED_VALUE"""),"#N/A") -> #N/A
E14: {=IF($C$8>=$C$7,SUM(XLOOKUP($C$7,Indicadores!$D$27:$D554,Indicadores!I$27:I554):XLOOKUP($C$8,Indicadores!$D$27:$D554,Indicadores!I$27:I554)),"Insira uma Data Final maior ou igual à Data Inicial")} -> #N/A | F14: {=IF($C$8>=$C$7,SUM(XLOOKUP($C$7,Indicadores!$D$27:$D554,Indicadores!J$27:J554):XLOOKUP($C$8,Indicadores!$D$27:$D554,Indicadores!J$27:J554)),"Insira uma Data Final maior ou igual à Data Inicial")} -> #N/A | G14: {=IF($C$8>=$C$7,SUM(XLOOKUP($C$7,Indicadores!$D$27:$D554,Indicadores!K$27:K554):XLOOKUP($C$8,Indicadores!$D$27:$D554,Indicadores!K$27:K554)),"Insira uma Data Final maior ou igual à Data Inicial")} -> #N/A | H14: {=IF($C$8>=$C$7,SUM(XLOOKUP($C$7,Indicadores!$D$27:$D554,Indicadores!L$27:L554):XLOOKUP($C$8,Indicadores!$D$27:$D554,Indicadores!L$27:L554)),"Insira uma Data Final maior ou igual à Data Inicial")} -> #N/A | I14: {=IF($C$8>=$C$7,SUM(XLOOKUP($C$7,Indicadores!$D$27:$D554,Indicadores!M$27:M554):XLOOKUP($C$8,Indicadores!$D$27:$D554,Indicadores!M$27:M554)),"Insira uma Data Final maior ou igual à Data Inicial")} -> #N/A
B15: Saídas Efetivas
B17: {=IF(C8>=C7,SUM(XLOOKUP(C7,Indicadores!$D$27:$D554,Indicadores!$F$27:$F554):XLOOKUP(C8,Indicadores!$D$27:$D554,Indicadores!$F$27:$F554)),"Insira uma Data Final maior ou igual à Data Inicial")} -> #N/A
E18: Breakeven | F18: Gasto Mensal Médio | G18: Valor Em Caixa | H18: Runway | I18: Margem Líquida
H19: {="(A partir de "&TEXT(XLOOKUP(H20,Indicadores!N27:N554,Indicadores!D27:D554),"MM")&"/"&TEXT(XLOOKUP(H20,Indicadores!N27:N554,Indicadores!D27:D554),"yyyy")&")"} -> (A partir de 01/2024)
B20: Faturamento Total | E20: {=IF($C$8>=$C$7,AVERAGE(XLOOKUP($C$7,Indicadores!$D$27:$D554,Indicadores!P$27:P554):XLOOKUP($C$8,Indicadores!$D$27:$D554,Indicadores!P$27:P554)),"Insira uma Data Final maior ou igual à Data Inicial")} -> 0 | F20: {=IF($C$8>=$C$7,AVERAGE(XLOOKUP($C$7,Indicadores!$D$27:$D554,Indicadores!I$27:I554):XLOOKUP($C$8,Indicadores!$D$27:$D554,Indicadores!I$27:I554)),"Insira uma Data Final maior ou igual à Data Inicial")} -> #N/A | G20: {=IF($C$8>=$C$7,SUM(XLOOKUP($C$7,Indicadores!$D$27:$D554,Indicadores!G$27:G554):XLOOKUP($C$8,Indicadores!$D$27:$D554,Indicadores!G$27:G554)),"Insira uma Data Final maior ou igual à Data Inicial")} -> #N/A | H20: {=IF($C$8>=$C$7,MAX(XLOOKUP($C$7,Indicadores!$D$27:$D554,Indicadores!N$27:N554):XLOOKUP($C$8,Indicadores!$D$27:$D554,Indicadores!N$27:N554)),"Insira uma Data Final maior ou igual à Data Inicial")} -> 0 | I20: {=IF($C$8>=$C$7,SUM(XLOOKUP($C$7,Indicadores!$D$27:$D554,Indicadores!G$27:G554):XLOOKUP($C$8,Indicadores!$D$27:$D554,Indicadores!G$27:G554))/SUM(XLOOKUP(C7,Indicadores!$D$27:$D554,Indicadores!$E$27:$E554):XLOOKUP(C8,Indicadores!$D$27:$D554,Indicadores!$E$27:$E554)),"Insira uma Data Final maior ou igual à Data Inicial")} -> #N/A
B22: {=IF(C8>=C7,SUM(XLOOKUP(C7,Indicadores!$D$27:$D554,Indicadores!$R$27:$R554):XLOOKUP(C8,Indicadores!$D$27:$D554,Indicadores!$R$27:$R554)),"Insira uma Data Final maior ou igual à Data Inicial")} -> #N/A
C27: Total
B28: =IFERROR(__xludf.DUMMYFUNCTION("Filter(teste!W8:W554,teste!T8:T554=""Entrada"")"),"Ensaio de Casal") -> Ensaio de Casal | C28: =SUM(AD8:AD554) -> #REF! | D28: =C28/$B$12 -> #REF!
B29: =IFERROR(__xludf.DUMMYFUNCTION("""COMPUTED_VALUE"""),"Ensaio simples") -> Ensaio simples | C29: =SUM(AE8:AE554) -> #REF! | D29: =C29/$B$12 -> #REF!
B30: =IFERROR(__xludf.DUMMYFUNCTION("""COMPUTED_VALUE"""),"Ensaio de 15 anos") -> Ensaio de 15 anos | C30: =SUM(AF8:AF554) -> #REF! | D30: =C30/$B$12 -> #REF!
B31: =IFERROR(__xludf.DUMMYFUNCTION("""COMPUTED_VALUE"""),"Ensaio de Formatura") -> Ensaio de Formatura | C31: =SUM(AG8:AG554) -> #REF! | D31: =C31/$B$12 -> #REF!
B32: =IFERROR(__xludf.DUMMYFUNCTION("""COMPUTED_VALUE"""),"Ensaio de Noivos") -> Ensaio de Noivos | C32: =SUM(AH8:AH554) -> #REF! | D32: =C32/$B$12 -> #REF!

Sheet teste
B1: Plano de Contas
A7: Fluxo | B7: Tipo de Custo | C7: Centro de Custo | D7: Nome | E7: Filtro p/ deletar CC inteiro | G7: =COUNTIFS(G8:G1022,"<>") -> 0 | H7: Filtro p/ deletar itens do TC inteiro | J7: =COUNTIFS(J8:J1022,"<>") -> 0 | K7: Filtro deletar CCs do TC e o próprio TC | L7: =COUNTIFS(L8:L1022,"<>") -> 0 | P7: Tipo de Custo | Q7: Centro de Custo | R7: Nome | T7: Fluxo | U7: Tipo de Custo | V7: Centro de Custo | W7: Nome
A8: Entrada | B8: Receitas | E8: =IFERROR(__xludf.DUMMYFUNCTION("IFERROR(FILTER(B7:D1022,C7:C1022='Gastos Fixos'!H10,D7:D1022<>""""),)"),"") | H8: =IFERROR(__xludf.DUMMYFUNCTION("IFERROR(FILTER(B7:D1022,B7:B1022='Gastos Fixos'!D10,C7:C1022<>"""",D7:D1022<>""""),)"),"") | K8: =IFERROR(__xludf.DUMMYFUNCTION("IFERROR(FILTER(B7:C1022,B7:B1022='Gastos Fixos'!D10,C7:C1022<>""""),)"),"") | P8: =IFERROR(__xludf.DUMMYFUNCTION("IFERROR(FILTER(B7:B1022,'Gastos Fixos'!C10=A7:A1022),)"),"") | Q8: =IFERROR(__xludf.DUMMYFUNCTION("IFERROR(FILTER(C7:C1022,'Gastos Fixos'!D10=B7:B1022,'Gastos Fixos'!C10=A7:A1022),)"),"") | R8: =IFERROR(__xludf.DUMMYFUNCTION("IFERROR(FILTER(D7:D1022,'Gastos Fixos'!H10=C7:C1022,'Gastos Fixos'!D10=B7:B1022,'Gastos Fixos'!C10=A7:A1022),)"),"") | T8: =IFERROR(__xludf.DUMMYFUNCTION("QUERY(A8:D1022,""select A,B,C,D where D is not null"")"),"Entrada") -> Entrada | U8: =IFERROR(__xludf.DUMMYFUNCTION("""COMPUTED_VALUE"""),"Receitas") -> Receitas | V8: =IFERROR(__xludf.DUMMYFUNCTION("""COMPUTED_VALUE"""),"Faturamento Baixo") -> Faturamento Baixo | W8: =IFERROR(__xludf.DUMMYFUNCTION("""COMPUTED_VALUE"""),"Ensaio de Casal") -> Ensaio de Casal
A9: Saída | B9: Investimentos | T9: =IFERROR(__xludf.DUMMYFUNCTION("""COMPUTED_VALUE"""),"Entrada") -> Entrada | U9: =IFERROR(__xludf.DUMMYFUNCTION("""COMPUTED_VALUE"""),"Receitas") -> Receitas | V9: =IFERROR(__xludf.DUMMYFUNCTION("""COMPUTED_VALUE"""),"Faturamento Baixo") -> Faturamento Baixo | W9: =IFERROR(__xludf.DUMMYFUNCTION("""COMPUTED_VALUE"""),"Ensaio simples") -> Ensaio simples
A10: Saída | B10: Custos Variáveis | T10: =IFERROR(__xludf.DUMMYFUNCTION("""COMPUTED_VALUE"""),"Entrada") -> Entrada | U10: =IFERROR(__xludf.DUMMYFUNCTION("""COMPUTED_VALUE"""),"Receitas") -> Receitas | V10: =IFERROR(__xludf.DUMMYFUNCTION("""COMPUTED_VALUE"""),"Faturamento Baixo") -> Faturamento Baixo | W10: =IFERROR(__xludf.DUMMYFUNCTION("""COMPUTED_VALUE"""),"Ensaio de 15 anos") -> Ensaio de 15 anos
A11: Saída | B11: Despesas | T11: =IFERROR(__xludf.DUMMYFUNCTION("""COMPUTED_VALUE"""),"Entrada") -> Entrada | U11: =IFERROR(__xludf.DUMMYFUNCTION("""COMPUTED_VALUE"""),"Receitas") -> Receitas | V11: =IFERROR(__xludf.DUMMYFUNCTION("""COMPUTED_VALUE"""),"Faturamento Alto") -> Faturamento Alto | W11: =IFERROR(__xludf.DUMMYFUNCTION("""COMPUTED_VALUE"""),"Ensaio de Formatura") -> Ensaio de Formatura
A12: Saída | B12: Custos Fixos | T12: =IFERROR(__xludf.DUMMYFUNCTION("""COMPUTED_VALUE"""),"Entrada") -> Entrada | U12: =IFERROR(__xludf.DUMMYFUNCTION("""COMPUTED_VALUE"""),"Receitas") -> Receitas | V12: =IFERROR(__xludf.DUMMYFUNCTION("""COMPUTED_VALUE"""),"Faturamento Alto") -> Faturamento Alto | W12: =IFERROR(__xludf.DUMMYFUNCTION("""COMPUTED_VALUE"""),"Ensaio de Noivos") -> Ensaio de Noivos
A13: Entrada | B13: Receitas | C13: Faturamento Baixo | T13: =IFERROR(__xludf.DUMMYFUNCTION("""COMPUTED_VALUE"""),"Saída") -> Saída | U13: =IFERROR(__xludf.DUMMYFUNCTION("""COMPUTED_VALUE"""),"Custos Fixos") -> Custos Fixos | V13: =IFERROR(__xludf.DUMMYFUNCTION("""COMPUTED_VALUE"""),"Infraestrutura") -> Infraestrutura | W13: =IFERROR(__xludf.DUMMYFUNCTION("""COMPUTED_VALUE"""),"Aluguel de Equipamentos") -> Aluguel de Equipamentos
A14: Entrada | B14: Receitas | C14: Faturamento Baixo | D14: Ensaio de Casal | T14: =IFERROR(__xludf.DUMMYFUNCTION("""COMPUTED_VALUE"""),"Saída") -> Saída | U14: =IFERROR(__xludf.DUMMYFUNCTION("""COMPUTED_VALUE"""),"Custos Fixos") -> Custos Fixos | V14: =IFERROR(__xludf.DUMMYFUNCTION("""COMPUTED_VALUE"""),"Infraestrutura") -> Infraestrutura | W14: =IFERROR(__xludf.DUMMYFUNCTION("""COMPUTED_VALUE"""),"Aluguel do Estúdio") -> Aluguel do Estúdio
A15: Entrada | B15: Receitas | C15: Faturamento Baixo | D15: Ensaio simples | T15: =IFERROR(__xludf.DUMMYFUNCTION("""COMPUTED_VALUE"""),"Saída") -> Saída | U15: =IFERROR(__xludf.DUMMYFUNCTION("""COMPUTED_VALUE"""),"Custos Fixos") -> Custos Fixos | V15: =IFERROR(__xludf.DUMMYFUNCTION("""COMPUTED_VALUE"""),"Infraestrutura") -> Infraestrutura | W15: =IFERROR(__xludf.DUMMYFUNCTION("""COMPUTED_VALUE"""),"CEB") -> CEB
A16: Entrada | B16: Receitas | C16: Faturamento Baixo | D16: Ensaio de 15 anos | T16: =IFERROR(__xludf.DUMMYFUNCTION("""COMPUTED_VALUE"""),"Saída") -> Saída | U16: =IFERROR(__xludf.DUMMYFUNCTION("""COMPUTED_VALUE"""),"Custos Fixos") -> Custos Fixos | V16: =IFERROR(__xludf.DUMMYFUNCTION("""COMPUTED_VALUE"""),"Pessoal") -> Pessoal | W16: =IFERROR(__xludf.DUMMYFUNCTION("""COMPUTED_VALUE"""),"Salário - Fotógrafos") -> Salário - Fotógrafos
A17: Entrada | B17: Receitas | C17: Faturamento Alto | T17: =IFERROR(__xludf.DUMMYFUNCTION("""COMPUTED_VALUE"""),"Saída") -> Saída | U17: =IFERROR(__xludf.DUMMYFUNCTION("""COMPUTED_VALUE"""),"Custos Fixos") -> Custos Fixos | V17: =IFERROR(__xludf.DUMMYFUNCTION("""COMPUTED_VALUE"""),"Pessoal") -> Pessoal | W17: =IFERROR(__xludf.DUMMYFUNCTION("""COMPUTED_VALUE"""),"Salário - Atendente") -> Salário - Atendente
A18: Entrada | B18: Receitas | C18: Faturamento Alto | D18: Ensaio de Formatura | T18: =IFERROR(__xludf.DUMMYFUNCTION("""COMPUTED_VALUE"""),"Saída") -> Saída | U18: =IFERROR(__xludf.DUMMYFUNCTION("""COMPUTED_VALUE"""),"Custos Fixos") -> Custos Fixos | V18: =IFERROR(__xludf.DUMMYFUNCTION("""COMPUTED_VALUE"""),"Pessoal") -> Pessoal | W18: =IFERROR(__xludf.DUMMYFUNCTION("""COMPUTED_VALUE"""),"Vale Transporte") -> Vale Transporte
A19: Entrada | B19: Receitas | C19: Faturamento Alto | D19: Ensaio de Noivos | T19: =IFERROR(__xludf.DUMMYFUNCTION("""COMPUTED_VALUE"""),"Saída") -> Saída | U19: =IFERROR(__xludf.DUMMYFUNCTION("""COMPUTED_VALUE"""),"Custos Fixos") -> Custos Fixos | V19: =IFERROR(__xludf.DUMMYFUNCTION("""COMPUTED_VALUE"""),"Pessoal") -> Pessoal | W19: =IFERROR(__xludf.DUMMYFUNCTION("""COMPUTED_VALUE"""),"Vale Alimentação") -> Vale Alimentação
A20: Saída | B20: Custos Fixos | C20: Infraestrutura | T20: =IFERROR(__xludf.DUMMYFUNCTION("""COMPUTED_VALUE"""),"Saída") -> Saída | U20: =IFERROR(__xludf.DUMMYFUNCTION("""COMPUTED_VALUE"""),"Custos Variáveis") -> Custos Variáveis | V20: =IFERROR(__xludf.DUMMYFUNCTION("""COMPUTED_VALUE"""),"Encargos Governo") -> Encargos Governo | W20: =IFERROR(__xludf.DUMMYFUNCTION("""COMPUTED_VALUE"""),"Impostos") -> Impostos
A21: Saída | B21: Custos Fixos | C21: Infraestrutura | D21: Aluguel de Equipamentos | T21: =IFERROR(__xludf.DUMMYFUNCTION("""COMPUTED_VALUE"""),"Saída") -> Saída | U21: =IFERROR(__xludf.DUMMYFUNCTION("""COMPUTED_VALUE"""),"Custos Variáveis") -> Custos Variáveis | V21: =IFERROR(__xludf.DUMMYFUNCTION("""COMPUTED_VALUE"""),"Encargos Sociais") -> Encargos Sociais | W21: =IFERROR(__xludf.DUMMYFUNCTION("""COMPUTED_VALUE"""),"13° Salário") -> 13° Salário
A22: Saída | B22: Custos Fixos | C22: Infraestrutura | D22: Aluguel do Estúdio | T22: =IFERROR(__xludf.DUMMYFUNCTION("""COMPUTED_VALUE"""),"Saída") -> Saída | U22: =IFERROR(__xludf.DUMMYFUNCTION("""COMPUTED_VALUE"""),"Despesas") -> Despesas | V22: =IFERROR(__xludf.DUMMYFUNCTION("""COMPUTED_VALUE"""),"Operacional") -> Operacional | W22: =IFERROR(__xludf.DUMMYFUNCTION("""COMPUTED_VALUE"""),"Internet") -> Internet
A23: Saída | B23: Custos Fixos | C23: Infraestrutura | D23: CEB | T23: =IFERROR(__xludf.DUMMYFUNCTION("""COMPUTED_VALUE"""),"Saída") -> Saída | U23: =IFERROR(__xludf.DUMMYFUNCTION("""COMPUTED_VALUE"""),"Despesas") -> Despesas | V23: =IFERROR(__xludf.DUMMYFUNCTION("""COMPUTED_VALUE"""),"Operacional") -> Operacional | W23: =IFERROR(__xludf.DUMMYFUNCTION("""COMPUTED_VALUE"""),"Telefone") -> Telefone
A24: Saída | B24: Custos Fixos | C24: Pessoal | T24: =IFERROR(__xludf.DUMMYFUNCTION("""COMPUTED_VALUE"""),"Saída") -> Saída | U24: =IFERROR(__xludf.DUMMYFUNCTION("""COMPUTED_VALUE"""),"Despesas") -> Despesas | V24: =IFERROR(__xludf.DUMMYFUNCTION("""COMPUTED_VALUE"""),"Operacional") -> Operacional | W24: =IFERROR(__xludf.DUMMYFUNCTION("""COMPUTED_VALUE"""),"Software") -> Software
A25: Saída | B25: Custos Fixos | C25: Pessoal | D25: Salário - Fotógrafos | T25: =IFERROR(__xludf.DUMMYFUNCTION("""COMPUTED_VALUE"""),"Saída") -> Saída | U25: =IFERROR(__xludf.DUMMYFUNCTION("""COMPUTED_VALUE"""),"Despesas") -> Despesas | V25: =IFERROR(__xludf.DUMMYFUNCTION("""COMPUTED_VALUE"""),"Operacional") -> Operacional | W25: =IFERROR(__xludf.DUMMYFUNCTION("""COMPUTED_VALUE"""),"CAESB") -> CAESB
A26: Saída | B26: Custos Fixos | C26: Pessoal | D26: Salário - Atendente | T26: =IFERROR(__xludf.DUMMYFUNCTION("""COMPUTED_VALUE"""),"Saída") -> Saída | U26: =IFERROR(__xludf.DUMMYFUNCTION("""COMPUTED_VALUE"""),"Despesas") -> Despesas | V26: =IFERROR(__xludf.DUMMYFUNCTION("""COMPUTED_VALUE"""),"Terceirizados") -> Terceirizados | W26: =IFERROR(__xludf.DUMMYFUNCTION("""COMPUTED_VALUE"""),"Contador") -> Contador
A27: Saída | B27: Custos Fixos | C27: Pessoal | D27: Vale Transporte | T27: =IFERROR(__xludf.DUMMYFUNCTION("""COMPUTED_VALUE"""),"Saída") -> Saída | U27: =IFERROR(__xludf.DUMMYFUNCTION("""COMPUTED_VALUE"""),"Despesas") -> Despesas | V27: =IFERROR(__xludf.DUMMYFUNCTION("""COMPUTED_VALUE"""),"Terceirizados") -> Terceirizados | W27: =IFERROR(__xludf.DUMMYFUNCTION("""COMPUTED_VALUE"""),"Marketing") -> Marketing
A28: Saída | B28: Custos Fixos | C28: Pessoal | D28: Vale Alimentação
A29: Saída | B29: Custos Variáveis | C29: Encargos Governo
A30: Saída | B30: Custos Variáveis | C30: Encargos Governo | D30: Impostos
A31: Saída | B31: Custos Variáveis | C31: Encargos Sociais
A32: Saída | B32: Custos Variáveis | C32: Encargos Sociais | D32: 13° Salário
A33: Saída | B33: Despesas | C33: Operacional
A34: Saída | B34: Despesas | C34: Operacional | D34: Internet
A35: Saída | B35: Despesas | C35: Operacional | D35: Telefone
A36: Saída | B36: Despesas | C36: Operacional | D36: Software
A37: Saída | B37: Despesas | C37: Operacional | D37: CAESB
A38: Saída | B38: Despesas | C38: Terceirizados
A39: Saída | B39: Despesas | C39: Terceirizados | D39: Contador
A40: Saída | B40: Despesas | C40: Terceirizados | D40: Marketing

Sheet Registro
B1: Registro
A6: 0 | C6: SEERRO(FILTER( 'Base de Dados'!A7:Q; ('Base de Dados'!A7:A = C16) + (C16 = ""); ('Base de Dados'!E7:E = C17) + (C17 = ""); ('Base de Dados'!C7:C = C18) + (C18 = ""); ('Base de Dados'!I7:I = C19) + (C19 = ""); ('Base de Dados'!D7:D = C20) + (C20 = ""));) | D6: FILTER(A10:L14; (D10:D14 <> "") * (E10:E14 <> "") * (F10:F14 <> "") * (G10:G14 <> "") * (I10:I14 <> "") * (J10:J14 <> ""))
B8: Registrar | AD8: =COUNTA($U$11:$U$15) -> 1
B9: ID | C9: Data | D9: Item | E9: Fluxo | F9: Tipo | G9: Centro | H9: Descrição | I9: Forma de pagamento | J9: Valor Total | K9: Parcelas | L9: Desconto | V9: ID | W9: Data | X9: Item | Y9: Fluxo | Z9: Tipo | AA9: Centro | AB9: Descrição | AC9: Forma de pagamento | AD9: Valor Total | AE9: Parcelas | AF9: Desconto
A10: 1 | C10: 45986 | D10: CAESB | E10: {=IFERROR(XLOOKUP(D10,teste!$W$8:$W2003,teste!$T$8:$T2003),)} -> Saída | F10: {=IFERROR(XLOOKUP(D10,teste!$W$8:$W2003,teste!$U$8:$U2003),)} -> Despesas | G10: {=IFERROR(XLOOKUP(D10,teste!$W$8:$W2003,teste!$V$8:$V2003),)} -> Operacional | I10: Parcelamento | J10: 2000 | K10: 10 | U10: =U11 -> 1 | V10: =V11 | W10: =W11 -> 45986 | X10: =X11 -> CAESB | Y10: =Y11 -> Saída | Z10: =Z11 -> Despesas | AA10: =AA11 -> Operacional | AB10: =AB11 | ... AF10: =AF11
A11: 2 | E11: {=IFERROR(XLOOKUP(D11,teste!$W$8:$W2003,teste!$T$8:$T2003),)} | F11: {=IFERROR(XLOOKUP(D11,teste!$W$8:$W2003,teste!$U$8:$U2003),)} | G11: {=IFERROR(XLOOKUP(D11,teste!$W$8:$W2003,teste!$V$8:$V2003),)} | U11: =IFERROR(__xludf.DUMMYFUNCTION("FILTER(A10:L14, (D10:D14 <> """") * (E10:E14 <> """") * (F10:F14 <> """") * (G10:G14 <> """"))"),1.0) -> 1 | W11: =IFERROR(__xludf.DUMMYFUNCTION("""COMPUTED_VALUE"""),45986.0) -> 45986 | X11: =IFERROR(__xludf.DUMMYFUNCTION("""COMPUTED_VALUE"""),"CAESB") -> CAESB | Y11: =IFERROR(__xludf.DUMMYFUNCTION("""COMPUTED_VALUE"""),"Saída") -> Saída | Z11: =IFERROR(__xludf.DUMMYFUNCTION("""COMPUTED_VALUE"""),"Despesas") -> Despesas | AA11: =IFERROR(__xludf.DUMMYFUNCTION("""COMPUTED_VALUE"""),"Operacional") -> Operacional | AC11: =IFERROR(__xludf.DUMMYFUNCTION("""COMPUTED_VALUE"""),"Parcelamento") -> Parcelamento | AD11: =IFERROR(__xludf.DUMMYFUNCTION("""COMPUTED_VALUE"""),2000.0) -> 2000 | AE11: =IFERROR(__xludf.DUMMYFUNCTION("""COMPUTED_VALUE"""),10.0) -> 10
A12: 3 | E12: {=IFERROR(XLOOKUP(D12,teste!$W$8:$W2003,teste!$T$8:$T2003),)} | F12: {=IFERROR(XLOOKUP(D12,teste!$W$8:$W2003,teste!$U$8:$U2003),)} | G12: {=IFERROR(XLOOKUP(D12,teste!$W$8:$W2003,teste!$V$8:$V2003),)}
A13: 4 | E13: {=IFERROR(XLOOKUP(D13,teste!$W$8:$W2003,teste!$T$8:$T2003),)} | F13: {=IFERROR(XLOOKUP(D13,teste!$W$8:$W2003,teste!$U$8:$U2003),)} | G13: {=IFERROR(XLOOKUP(D13,teste!$W$8:$W2003,teste!$V$8:$V2003),)}
A14: 5 | E14: {=IFERROR(XLOOKUP(D14,teste!$W$8:$W2003,teste!$T$8:$T2003),)} | F14: {=IFERROR(XLOOKUP(D14,teste!$W$8:$W2003,teste!$U$8:$U2003),)} | G14: {=IFERROR(XLOOKUP(D14,teste!$W$8:$W2003,teste!$V$8:$V2003),)}
A15: Proteger intervalo acima (A10:A14) e esconder seus números | E15: Proteger intervalo acima (E10:G14)
C18: Pesquisar | E18: Sim
C19: ID | D19: Forma de Pagamento | E19: Item
D20: À vista
C24: ID | D24: Data | E24: Confirmação de Pagamento | F24: Item | G24: Fluxo | H24: Tipo | I24: Centro | J24: Descrição | K24: Forma de pagamento | L24: Parcela | M24: Valor Total | N24: Desconto | O24: Valor final | P24: Dia | Q24: Mês | R24: Ano | S24: N°
C25: =IFERROR(__xludf.DUMMYFUNCTION("IFERROR(IF($E$18=""Sim"", FILTER( 'Base de Dados'!$A$7:$Q2003, ARRAYFORMULA(SEARCH($E$20,'Base de Dados'!$D$7:$D2003)) + ($E$20 = """"), ARRAYFORMULA(SEARCH($D$20,'Base de Dados'!$I$7:$I2003)) + ($D$20 = """"),ARRAYFORMULA(SEARCH($C$20,'Base de Dados'!$A$"&"7:$A2003)) + ($C$20 = """"),$A$6<>'Base de Dados'!$Q$7:$Q2003,$A$6<>'Base de Dados'!$A$7:$A2003),))"),"")

Sheet Registro de Fichas Técnicas
B1: Registro de Fichas Técnicas
B8: Registro de Fichas Técnicas
B10: Nome | D10: Custo Total
B11: Ficha Técnica 1 | D11: =SUM(F15:F35) -> 0
B14: Recurso Utilizado | C14: Quantidade | D14: Unidade de Medida | E14: Observações | F14: Custo Unitario
F15: {=XLOOKUP($B15,'Registro de Insumos'!$D:$D,'Registro de Insumos'!$H:$H,) * $C15} -> 0
F16: {=XLOOKUP($B16,'Registro de Insumos'!$D:$D,'Registro de Insumos'!$H:$H,) * $C16} -> 0
F17: {=XLOOKUP($B17,'Registro de Insumos'!$D:$D,'Registro de Insumos'!$H:$H,) * $C17} -> 0
F18: {=XLOOKUP($B18,'Registro de Insumos'!$D:$D,'Registro de Insumos'!$H:$H,) * $C18} -> 0
F19: {=XLOOKUP($B19,'Registro de Insumos'!$D:$D,'Registro de Insumos'!$H:$H,) * $C19} -> 0
F20: {=XLOOKUP($B20,'Registro de Insumos'!$D:$D,'Registro de Insumos'!$H:$H,) * $C20} -> 0
F21: {=XLOOKUP($B21,'Registro de Insumos'!$D:$D,'Registro de Insumos'!$H:$H,) * $C21} -> 0
F22: {=XLOOKUP($B22,'Registro de Insumos'!$D:$D,'Registro de Insumos'!$H:$H,) * $C22} -> 0
F23: {=XLOOKUP($B23,'Registro de Insumos'!$D:$D,'Registro de Insumos'!$H:$H,) * $C23} -> 0
F24: {=XLOOKUP($B24,'Registro de Insumos'!$D:$D,'Registro de Insumos'!$H:$H,) * $C24} -> 0
F25: {=XLOOKUP($B25,'Registro de Insumos'!$D:$D,'Registro de Insumos'!$H:$H,) * $C25} -> 0
F26: {=XLOOKUP($B26,'Registro de Insumos'!$D:$D,'Registro de Insumos'!$H:$H,) * $C26} -> 0
... F35: {=XLOOKUP($B35,'Registro de Insumos'!$D:$D,'Registro de Insumos'!$H:$H,) * $C35} -> 0
B39: ID Ficha-Técnica | C39: Nome | D39: Recurso Utilizado | E39: Quantidade | F39: Unidade de Medida | G39: Observações | H39: Custo Unitario

Sheet Base de Salários
B1: Base de Salários
A6: 0 | C6: SEERRO(FILTER( 'Base de Dados'!A7:Q; ('Base de Dados'!A7:A = C16) + (C16 = ""); ('Base de Dados'!E7:E = C17) + (C17 = ""); ('Base de Dados'!C7:C = C18) + (C18 = ""); ('Base de Dados'!I7:I = C19) + (C19 = ""); ('Base de Dados'!D7:D = C20) + (C20 = ""));) | D6: FILTER(A10:L14; (D10:D14 <> "") * (E10:E14 <> "") * (F10:F14 <> "") * (G10:G14 <> "") * (I10:I14 <> "") * (J10:J14 <> ""))
B8: Editar | C8: Registro | AD8: =COUNTA($U$11:$U$15) -> 1
B9: Registro | C9: Cargo | D9: Área | E9: Quantidade | F9: Remuneração | G9: Horas trabalhadas p/ mês | U9: ID | V9: Data | W9: Item | X9: Fluxo | Y9: Tipo | Z9: Centro | AA9: Descrição | AB9: Forma de pagamento | AC9: Valor Total | AD9: Parcelas | AE9: Desconto
U10: =U11 -> #N/A | V10: =V11 | W10: =W11 | X10: =X11 | Y10: =Y11 | Z10: =Z11 | AA10: =AA11 | AB10: =AB11 | ... AF10: =AF11
U11: =IFERROR(__xludf.DUMMYFUNCTION("FILTER(A10:L14, (D10:D14 <> """") * (E10:E14 <> """") * (F10:F14 <> """") * (G10:G14 <> """"))"),"#N/A") -> #N/A
I12: Faturamento Estimado | J12: ='Gastos Fixos'!H9 -> 10100428
I13: Soma das Despesas | J13: =SUM(G18:G996) -> 85281.93
I14: % Salários vs Faturamento | J14: =J13/J12 -> 0.0084433977
C17: ID | D17: Profissional | E17: Área | F17: Quantidade | G17: Remuneração | H17: Horas trabalhadas p/ mês | I17: Salário [Hora] | J17: Salário [Dia]
C18: 1 | D18: Ajudante Geral - Ricardo | E18: Montagem | F18: 1 | G18: 3094.2 | H18: 220 | I18: 14.064545 | J18: 112.51636
C19: 2 | D19: Ajudante Geral - Tierry | E19: Montagem | F19: 1 | G19: 3094.2 | H19: 220 | I19: 14.064545 | J19: 112.51636
C20: 3 | D20: Almoxarifado | E20: Almoxarifado | F20: 1 | G20: 3687.8 | H20: 220 | I20: 16.762727 | J20: 134.10182
C21: 4 | D21: Analista de RH | E21: Engenharia | F21: 1 | G21: 5459 | H21: 220 | I21: 24.813636 | J21: 198.50909
C22: 5 | D22: Assistente Administrativo | E22: Engenharia | F22: 1 | G22: 3935.47 | H22: 220 | I22: 17.8885 | J22: 143.108
C23: 6 | D23: Auxiliar de Eletricista - Alisson | E23: Montagem | F23: 1 | G23: 3602.8 | H23: 220 | I23: 16.376364 | J23: 131.01091
C24: 7 | D24: Auxiliar de Eletricista - Bruno | E24: Montagem | F24: 1 | G24: 3547.8 | H24: 220 | I24: 16.126364 | J24: 129.01091
C25: 8 | D25: Auxiliar de Eletricista - Manoel | E25: Montagem | F25: 1 | G25: 3602.8 | H25: 220 | I25: 16.376364 | J25: 131.01091
C26: 9 | D26: Auxiliar de Limpeza | E26: Limpeza | F26: 1 | G26: 3094.2 | H26: 220 | I26: 14.064545 | J26: 112.51636
C27: 10 | D27: Eletricista - Antonio | E27: Montagem | F27: 1 | G27: 4498.8 | H27: 220 | I27: 20.449091 | J27: 163.59273
C28: 11 | D28: Eletricista - Joeilson | E28: Montagem | F28: 1 | G28: 4864.32 | H28: 220 | I28: 22.110545 | J28: 176.88436
C29: 12 | D29: Eletricista - Wandercy | E29: Montagem | F29: 1 | G29: 4406.4 | H29: 220 | I29: 20.029091 | J29: 160.23273
... C36: 19 | D36: Serralheiro | E36: Serralheria | F36: 1 | G36: 4392.92 | H36: 220 | I36: 19.967818 | J36: 159.74255

Sheet Config_Unidades
A1: Unidade
A2: gramas
A3: kg
A4: litros
A5: mg
A6: caixa
A7: pacote
A8: Cristiano Rose

Sheet Precificação Produto | Custo Co
B1: Preço de Venda de Produto com Custo Conhecido
E6: FILTER(A10:L14; (D10:D14 <> "") * (E10:E14 <> "") * (F10:F14 <> "") * (G10:G14 <> "") * (I10:I14 <> "") * (J10:J14 <> ""))
C7: Seleção de ficha | J7: Informações Extras | M7: DRE do Projeto | O7: Individual | R7: Lote
B9: Editar | C9: Código do Produto | D9: Nome do Item | E9: Quantidade | F9: Quantidade Referência | G9: Valor Referência | H9: Valor Custo | J9: Margem de Lucro | K9: Porcentagem | M9: DRE - Projeto | O9: Valor | P9: % do Preço | R9: Valor | S9: % do Preço
J10: Margem Desejada | K10: 0.1 | M10: Preço de Venda | O10: =K27 -> 0 | P10: =K14*K25/O10 -> #DIV/0! | R10: 0.3 | S10: 0.3
J12: Unidades desse Lote | K12: Quantidade Unitária | M12: =#REF! -> #REF! | O12: =IFERROR(P12*$O$10,"") -> 0 | P12: =IFERROR(VLOOKUP(M12,'Gastos Variáveis'!D:E,2,FALSE),"") | R12: =#REF! -> #REF! | S12: =#REF! -> #REF!
J13: Quantidade produzida | K13: 10 | M13: =#REF! -> #REF! | O13: =IFERROR(P13*$O$10,"") -> 0 | P13: =IFERROR(VLOOKUP(M13,'Gastos Variáveis'!D:E,2,FALSE),"") | R13: =#REF! -> #REF! | S13: =#REF! -> #REF!
J14: Custo Direto Unitário | K14: =(SUM(H10:H9999))/K13 -> 0 | M14: =#REF! -> #REF! | O14: =IFERROR(P14*$O$10,"") -> 0 | P14: =IFERROR(VLOOKUP(M14,'Gastos Variáveis'!D:E,2,FALSE),"") | R14: =#REF! -> #REF! | S14: =#REF! -> #REF!
F15: =IFERROR(VLOOKUP(D15,'Registro de Insumos'!D:G,3,FALSE),"") | G15: =IFERROR(VLOOKUP(D15,'Registro de Insumos'!D:G,4,FALSE),"") | H15: =IFERROR((G15/F15)*E15,"") | M15: ='Gastos Variáveis'!D14 -> Impostos | O15: =IFERROR(P15*$O$10,"") -> 0 | P15: =IFERROR(VLOOKUP(M15,'Gastos Variáveis'!D:E,2,FALSE),"") -> 0.0094 | R15: ='Gastos Variáveis'!I14 | S15: ='Gastos Variáveis'!J14
F16: =IFERROR(VLOOKUP(D16,'Registro de Insumos'!D:G,3,FALSE),"") | G16: =IFERROR(VLOOKUP(D16,'Registro de Insumos'!D:G,4,FALSE),"") | H16: =IFERROR((G16/F16)*E16,"") | O16: =IFERROR(P16*$O$10,"") -> 0 | P16: =IFERROR(VLOOKUP(M16,'Gastos Variáveis'!D:E,2,FALSE),"") | R16: ='Gastos Variáveis'!I15 | S16: ='Gastos Variáveis'!J15
F17: =IFERROR(VLOOKUP(D17,'Registro de Insumos'!D:G,3,FALSE),"") | G17: =IFERROR(VLOOKUP(D17,'Registro de Insumos'!D:G,4,FALSE),"") | H17: =IFERROR((G17/F17)*E17,"") | J17: Precificação do Produto | M17: ='Gastos Variáveis'!D16 | O17: =IFERROR(P17*$O$10,"") -> 0 | P17: =IFERROR(VLOOKUP(M17,'Gastos Variáveis'!D:E,2,FALSE),"") | R17: ='Gastos Variáveis'!I16 | S17: ='Gastos Variáveis'!J16
F18: =IFERROR(VLOOKUP(D18,'Registro de Insumos'!D:G,3,FALSE),"") | G18: =IFERROR(VLOOKUP(D18,'Registro de Insumos'!D:G,4,FALSE),"") | H18: =IFERROR((G18/F18)*E18,"") | I18: Horas trabalhadas p/ mês | M18: ='Gastos Variáveis'!D17 | O18: =IFERROR(P18*$O$10,"") -> 0 | P18: =IFERROR(VLOOKUP(M18,'Gastos Variáveis'!D:E,2,FALSE),"") | R18: ='Gastos Variáveis'!I17 | S18: ='Gastos Variáveis'!J17
F19: =IFERROR(VLOOKUP(D19,'Registro de Insumos'!D:G,3,FALSE),"") | G19: =IFERROR(VLOOKUP(D19,'Registro de Insumos'!D:G,4,FALSE),"") | H19: =IFERROR((G19/F19)*E19,"") | I19: 160 | J19: Informações | K19: Valor | M19: ='Gastos Variáveis'!D18 | O19: =IFERROR(P19*$O$10,"") -> 0 | P19: =IFERROR(VLOOKUP(M19,'Gastos Variáveis'!D:E,2,FALSE),"") | R19: ='Gastos Variáveis'!I18 | S19: ='Gastos Variáveis'!J18
F20: =IFERROR(VLOOKUP(D20,'Registro de Insumos'!D:G,3,FALSE),"") | G20: =IFERROR(VLOOKUP(D20,'Registro de Insumos'!D:G,4,FALSE),"") | H20: =IFERROR((G20/F20)*E20,"") | I20: 176 | J20: Custo Fixo | K20: ='Gastos Fixos'!H11 -> 0.20082555 | M20: Total Custos Variáveis | O20: 0.3 | P20: 0.3 | R20: 0.3 | S20: 0.3
F21: =IFERROR(VLOOKUP(D21,'Registro de Insumos'!D:G,3,FALSE),"") | G21: =IFERROR(VLOOKUP(D21,'Registro de Insumos'!D:G,4,FALSE),"") | H21: =IFERROR((G21/F21)*E21,"") | I21: 176 | J21: Custo Variável | K21: ='Gastos Variáveis'!H9 -> 0.0094 | M21: Total Custos Fixos | O21: 0.3 | P21: 0.3 | R21: 0.3 | S21: 0.3
F22: =IFERROR(VLOOKUP(D22,'Registro de Insumos'!D:G,3,FALSE),"") | G22: =IFERROR(VLOOKUP(D22,'Registro de Insumos'!D:G,4,FALSE),"") | H22: =IFERROR((G22/F22)*E22,"") | J22: Margem | K22: =K10 -> 0.1 | M22: Custo do Produto | O22: 0.3 | P22: 0.3 | R22: 0.3 | S22: 0.3
F23: =IFERROR(VLOOKUP(D23,'Registro de Insumos'!D:G,3,FALSE),"") | G23: =IFERROR(VLOOKUP(D23,'Registro de Insumos'!D:G,4,FALSE),"") | H23: =IFERROR((G23/F23)*E23,"") | J23: Salários | K23: ='Base de Salários'!J14 -> 0.0084433977 | M23: Total de Custos | O23: 0.3 | P23: 0.3 | R23: 0.3 | S23: 0.3
F24: =IFERROR(VLOOKUP(D24,'Registro de Insumos'!D:G,3,FALSE),"") | G24: =IFERROR(VLOOKUP(D24,'Registro de Insumos'!D:G,4,FALSE),"") | H24: =IFERROR((G24/F24)*E24,"") | J24: Soma | K24: =SUM(K20:K23) -> 0.31866895
F25: =IFERROR(VLOOKUP(D25,'Registro de Insumos'!D:G,3,FALSE),"") | G25: =IFERROR(VLOOKUP(D25,'Registro de Insumos'!D:G,4,FALSE),"") | H25: =IFERROR((G25/F25)*E25,"") | J25: Markup | K25: =1/(1-(K20+K21+K22+K23)) -> 1.4677153 | M25: Margem de Lucro | O25: 0.3 | P25: 0.3 | R25: 0.3 | S25: 0.3
F26: =IFERROR(VLOOKUP(D26,'Registro de Insumos'!D:G,3,FALSE),"") | G26: =IFERROR(VLOOKUP(D26,'Registro de Insumos'!D:G,4,FALSE),"") | H26: =IFERROR((G26/F26)*E26,"")
F27: =IFERROR(VLOOKUP(D27,'Registro de Insumos'!D:G,3,FALSE),"") | G27: =IFERROR(VLOOKUP(D27,'Registro de Insumos'!D:G,4,FALSE),"") | H27: =IFERROR((G27/F27)*E27,"") | J27: Preço de Venda | K27: =K14*K25 -> 0
F28: =IFERROR(VLOOKUP(D28,'Registro de Insumos'!D:G,3,FALSE),"") | G28: =IFERROR(VLOOKUP(D28,'Registro de Insumos'!D:G,4,FALSE),"") | H28: =IFERROR((G28/F28)*E28,"")
F29: =IFERROR(VLOOKUP(D29,'Registro de Insumos'!D:G,3,FALSE),"") | G29: =IFERROR(VLOOKUP(D29,'Registro de Insumos'!D:G,4,FALSE),"") | H29: =IFERROR((G29/F29)*E29,"")
F30: =IFERROR(VLOOKUP(D30,'Registro de Insumos'!D:G,3,FALSE),"") | G30: =IFERROR(VLOOKUP(D30,'Registro de Insumos'!D:G,4,FALSE),"") | H30: =IFERROR((G30/F30)*E30,"")
F31: =IFERROR(VLOOKUP(D31,'Registro de Insumos'!D:G,3,FALSE),"") | G31: =IFERROR(VLOOKUP(D31,'Registro de Insumos'!D:G,4,FALSE),"") | H31: =IFERROR((G31/F31)*E31,"")
F32: =IFERROR(VLOOKUP(D32,'Registro de Insumos'!D:G,3,FALSE),"") | G32: =IFERROR(VLOOKUP(D32,'Registro de Insumos'!D:G,4,FALSE),"") | H32: =IFERROR((G32/F32)*E32,"")
F33: =IFERROR(VLOOKUP(D33,'Registro de Insumos'!D:G,3,FALSE),"") | G33: =IFERROR(VLOOKUP(D33,'Registro de Insumos'!D:G,4,FALSE),"") | H33: =IFERROR((G33/F33)*E33,"")
F34: =IFERROR(VLOOKUP(D34,'Registro de Insumos'!D:G,3,FALSE),"") | G34: =IFERROR(VLOOKUP(D34,'Registro de Insumos'!D:G,4,FALSE),"") | H34: =IFERROR((G34/F34)*E34,"")
F35: =IFERROR(VLOOKUP(D35,'Registro de Insumos'!D:G,3,FALSE),"") | G35: =IFERROR(VLOOKUP(D35,'Registro de Insumos'!D:G,4,FALSE),"") | H35: =IFERROR((G35/F35)*E35,"")
F36: =IFERROR(VLOOKUP(D36,'Registro de Insumos'!D:G,3,FALSE),"") | G36: =IFERROR(VLOOKUP(D36,'Registro de Insumos'!D:G,4,FALSE),"") | H36: =IFERROR((G36/F36)*E36,"")
F37: =IFERROR(VLOOKUP(D37,'Registro de Insumos'!D:G,3,FALSE),"") | G37: =IFERROR(VLOOKUP(D37,'Registro de Insumos'!D:G,4,FALSE),"") | H37: =IFERROR((G37/F37)*E37,"")
F38: =IFERROR(VLOOKUP(D38,'Registro de Insumos'!D:G,3,FALSE),"") | G38: =IFERROR(VLOOKUP(D38,'Registro de Insumos'!D:G,4,FALSE),"") | H38: =IFERROR((G38/F38)*E38,"")
F39: =IFERROR(VLOOKUP(D39,'Registro de Insumos'!D:G,3,FALSE),"") | G39: =IFERROR(VLOOKUP(D39,'Registro de Insumos'!D:G,4,FALSE),"") | H39: =IFERROR((G39/F39)*E39,"")
... F101: =IFERROR(VLOOKUP(D101,'Registro de Insumos'!D:G,3,FALSE),"") | G101: =IFERROR(VLOOKUP(D101,'Registro de Insumos'!D:G,4,FALSE),"") | H101: =IFERROR((G101/F101)*E101,"")

Sheet Precificação Produto | Custo De
B1: Preço de Venda de Produto com Preço Desconhecido
A6: 0 | C6: SEERRO(FILTER( 'Base de Dados'!A7:Q; ('Base de Dados'!A7:A = C16) + (C16 = ""); ('Base de Dados'!E7:E = C17) + (C17 = ""); ('Base de Dados'!C7:C = C18) + (C18 = ""); ('Base de Dados'!I7:I = C19) + (C19 = ""); ('Base de Dados'!D7:D = C20) + (C20 = ""));) | D6: FILTER(A10:L14; (D10:D14 <> "") * (E10:E14 <> "") * (F10:F14 <> "") * (G10:G14 <> "") * (I10:I14 <> "") * (J10:J14 <> ""))
C7: Preenchimento de Insumos | I7: Informações Extras
B9: Editar | C9: Nome do Item | D9: Quantidade | E9: Quantidade Referência | F9: Valor Referência | G9: Valor Custo | I9: Margem de Lucro | J9: Porcentagem
B10: Registro | C10: BLOCO CONTATO AUXILIAR FRONTAL BFCA 3NA+1NF COM PARAFUSO UI MAX=660/690 VOLTS AZUL MINICONTATOR CWCA | D10: 20 | E10: =IFERROR(VLOOKUP(C10,'Registro de Insumos'!D:G,3,FALSE),"") -> 1 | F10: =IFERROR(VLOOKUP(C10,'Registro de Insumos'!D:G,4,FALSE),"") -> 24.59 | G10: =IFERROR((F10/E10)*D10,"") -> 491.8 | I10: Margem Desejada | J10: 0.4
C11: BLOCO CONTATO AUXILIAR FRONTAL BFCA 3NA+1NF COM PARAFUSO UI MAX=660/690 VOLTS AZUL MINICONTATOR CWCA | D11: 43 | E11: =IFERROR(VLOOKUP(C11,'Registro de Insumos'!D:G,3,FALSE),"") -> 1 | F11: =IFERROR(VLOOKUP(C11,'Registro de Insumos'!D:G,4,FALSE),"") -> 24.59 | G11: =IFERROR((F11/E11)*D11,"") -> 1057.37
C12: FCT-06-SU 07/26 | D12: 56 | E12: =IFERROR(VLOOKUP(C12,'Registro de Insumos'!D:G,3,FALSE),"") -> 1 | F12: =IFERROR(VLOOKUP(C12,'Registro de Insumos'!D:G,4,FALSE),"") -> 0 | G12: =IFERROR((F12/E12)*D12,"") -> 0 | I12: Unidades desse Lote | J12: Quantidade Unitária
C13: CH ALLEN 6MM SATA | D13: 13 | E13: =IFERROR(VLOOKUP(C13,'Registro de Insumos'!D:G,3,FALSE),"") -> 1 | F13: =IFERROR(VLOOKUP(C13,'Registro de Insumos'!D:G,4,FALSE),"") -> 6 | G13: =IFERROR((F13/E13)*D13,"") -> 78 | I13: Quantidade Produzida | J13: 1
E14: =IFERROR(VLOOKUP(C14,'Registro de Insumos'!D:G,3,FALSE),"") | F14: =IFERROR(VLOOKUP(C14,'Registro de Insumos'!D:G,4,FALSE),"") | G14: =IFERROR((F14/E14)*D14,"") | I14: Custo Unitário | J14: =(SUM(G10:G9999))/J13 -> 1627.17
E15: =IFERROR(VLOOKUP(C15,'Registro de Insumos'!D:G,3,FALSE),"") | F15: =IFERROR(VLOOKUP(C15,'Registro de Insumos'!D:G,4,FALSE),"") | G15: =IFERROR((F15/E15)*D15,"")
E16: =IFERROR(VLOOKUP(C16,'Registro de Insumos'!D:G,3,FALSE),"") | F16: =IFERROR(VLOOKUP(C16,'Registro de Insumos'!D:G,4,FALSE),"") | G16: =IFERROR((F16/E16)*D16,"")
E17: =IFERROR(VLOOKUP(C17,'Registro de Insumos'!D:G,3,FALSE),"") | F17: =IFERROR(VLOOKUP(C17,'Registro de Insumos'!D:G,4,FALSE),"") | G17: =IFERROR((F17/E17)*D17,"") | I17: Precificação do Produto
E18: =IFERROR(VLOOKUP(C18,'Registro de Insumos'!D:G,3,FALSE),"") | F18: =IFERROR(VLOOKUP(C18,'Registro de Insumos'!D:G,4,FALSE),"") | G18: =IFERROR((F18/E18)*D18,"") | H18: Horas trabalhadas p/ mês
E19: =IFERROR(VLOOKUP(C19,'Registro de Insumos'!D:G,3,FALSE),"") | F19: =IFERROR(VLOOKUP(C19,'Registro de Insumos'!D:G,4,FALSE),"") | G19: =IFERROR((F19/E19)*D19,"") | H19: 160 | I19: Informações | J19: Valor
E20: =IFERROR(VLOOKUP(C20,'Registro de Insumos'!D:G,3,FALSE),"") | F20: =IFERROR(VLOOKUP(C20,'Registro de Insumos'!D:G,4,FALSE),"") | G20: =IFERROR((F20/E20)*D20,"") | H20: 176 | I20: Custo Fixo | J20: ='Gastos Fixos'!H11 -> 0.20082555
E21: =IFERROR(VLOOKUP(C21,'Registro de Insumos'!D:G,3,FALSE),"") | F21: =IFERROR(VLOOKUP(C21,'Registro de Insumos'!D:G,4,FALSE),"") | G21: =IFERROR((F21/E21)*D21,"") | H21: 176 | I21: Custo Variável | J21: ='Gastos Variáveis'!H9 -> 0.0094
E22: =IFERROR(VLOOKUP(C22,'Registro de Insumos'!D:G,3,FALSE),"") | F22: =IFERROR(VLOOKUP(C22,'Registro de Insumos'!D:G,4,FALSE),"") | G22: =IFERROR((F22/E22)*D22,"") | I22: Margem | J22: =J10 -> 0.4
E23: =IFERROR(VLOOKUP(C23,'Registro de Insumos'!D:G,3,FALSE),"") | F23: =IFERROR(VLOOKUP(C23,'Registro de Insumos'!D:G,4,FALSE),"") | G23: =IFERROR((F23/E23)*D23,"") | I23: Salários | J23: ='Base de Salários'!J14 -> 0.0084433977
E24: =IFERROR(VLOOKUP(C24,'Registro de Insumos'!D:G,3,FALSE),"") | F24: =IFERROR(VLOOKUP(C24,'Registro de Insumos'!D:G,4,FALSE),"") | G24: =IFERROR((F24/E24)*D24,"") | I24: Soma | J24: =SUM(J20:J23) -> 0.61866895
E25: =IFERROR(VLOOKUP(C25,'Registro de Insumos'!D:G,3,FALSE),"") | F25: =IFERROR(VLOOKUP(C25,'Registro de Insumos'!D:G,4,FALSE),"") | G25: =IFERROR((F25/E25)*D25,"") | I25: Markup | J25: =1/(1-(J20+J21+J22+J23)) -> 2.6223933
E26: =IFERROR(VLOOKUP(C26,'Registro de Insumos'!D:G,3,FALSE),"") | F26: =IFERROR(VLOOKUP(C26,'Registro de Insumos'!D:G,4,FALSE),"") | G26: =IFERROR((F26/E26)*D26,"")
E27: =IFERROR(VLOOKUP(C27,'Registro de Insumos'!D:G,3,FALSE),"") | F27: =IFERROR(VLOOKUP(C27,'Registro de Insumos'!D:G,4,FALSE),"") | G27: =IFERROR((F27/E27)*D27,"") | I27: Preço de Venda | J27: =J14*J25 -> 4267.0798
E28: =IFERROR(VLOOKUP(C28,'Registro de Insumos'!D:G,3,FALSE),"") | F28: =IFERROR(VLOOKUP(C28,'Registro de Insumos'!D:G,4,FALSE),"") | G28: =IFERROR((F28/E28)*D28,"")
E29: =IFERROR(VLOOKUP(C29,'Registro de Insumos'!D:G,3,FALSE),"") | F29: =IFERROR(VLOOKUP(C29,'Registro de Insumos'!D:G,4,FALSE),"") | G29: =IFERROR((F29/E29)*D29,"")
E30: =IFERROR(VLOOKUP(C30,'Registro de Insumos'!D:G,3,FALSE),"") | F30: =IFERROR(VLOOKUP(C30,'Registro de Insumos'!D:G,4,FALSE),"") | G30: =IFERROR((F30/E30)*D30,"")
E31: =IFERROR(VLOOKUP(C31,'Registro de Insumos'!D:G,3,FALSE),"") | F31: =IFERROR(VLOOKUP(C31,'Registro de Insumos'!D:G,4,FALSE),"") | G31: =IFERROR((F31/E31)*D31,"")
E32: =IFERROR(VLOOKUP(C32,'Registro de Insumos'!D:G,3,FALSE),"") | F32: =IFERROR(VLOOKUP(C32,'Registro de Insumos'!D:G,4,FALSE),"") | G32: =IFERROR((F32/E32)*D32,"")
E33: =IFERROR(VLOOKUP(C33,'Registro de Insumos'!D:G,3,FALSE),"") | F33: =IFERROR(VLOOKUP(C33,'Registro de Insumos'!D:G,4,FALSE),"") | G33: =IFERROR((F33/E33)*D33,"")
E34: =IFERROR(VLOOKUP(C34,'Registro de Insumos'!D:G,3,FALSE),"") | F34: =IFERROR(VLOOKUP(C34,'Registro de Insumos'!D:G,4,FALSE),"") | G34: =IFERROR((F34/E34)*D34,"")
E35: =IFERROR(VLOOKUP(C35,'Registro de Insumos'!D:G,3,FALSE),"") | F35: =IFERROR(VLOOKUP(C35,'Registro de Insumos'!D:G,4,FALSE),"") | G35: =IFERROR((F35/E35)*D35,"")
E36: =IFERROR(VLOOKUP(C36,'Registro de Insumos'!D:G,3,FALSE),"") | F36: =IFERROR(VLOOKUP(C36,'Registro de Insumos'!D:G,4,FALSE),"") | G36: =IFERROR((F36/E36)*D36,"")
E37: =IFERROR(VLOOKUP(C37,'Registro de Insumos'!D:G,3,FALSE),"") | F37: =IFERROR(VLOOKUP(C37,'Registro de Insumos'!D:G,4,FALSE),"") | G37: =IFERROR((F37/E37)*D37,"")
E38: =IFERROR(VLOOKUP(C38,'Registro de Insumos'!D:G,3,FALSE),"") | F38: =IFERROR(VLOOKUP(C38,'Registro de Insumos'!D:G,4,FALSE),"") | G38: =IFERROR((F38/E38)*D38,"")
E39: =IFERROR(VLOOKUP(C39,'Registro de Insumos'!D:G,3,FALSE),"") | F39: =IFERROR(VLOOKUP(C39,'Registro de Insumos'!D:G,4,FALSE),"") | G39: =IFERROR((F39/E39)*D39,"")
... E101: =IFERROR(VLOOKUP(C101,'Registro de Insumos'!D:G,3,FALSE),"") | F101: =IFERROR(VLOOKUP(C101,'Registro de Insumos'!D:G,4,FALSE),"") | G101: =IFERROR((F101/E101)*D101,"")

Sheet Precificação Serviços | Custo D
B1: Preço de Venda de Serviço com Preço Desconhecido
A6: 0 | C6: SEERRO(FILTER( 'Base de Dados'!A7:Q; ('Base de Dados'!A7:A = C16) + (C16 = ""); ('Base de Dados'!E7:E = C17) + (C17 = ""); ('Base de Dados'!C7:C = C18) + (C18 = ""); ('Base de Dados'!I7:I = C19) + (C19 = ""); ('Base de Dados'!D7:D = C20) + (C20 = ""));) | D6: FILTER(A10:L14; (D10:D14 <> "") * (E10:E14 <> "") * (F10:F14 <> "") * (G10:G14 <> "") * (I10:I14 <> "") * (J10:J14 <> ""))
C7: Preenchimento de Insumos | I7: Informações Extras | L7: DRE do Projeto | N7: Individual | Q7: Lote
B9: Editar | C9: Nome do Item | D9: Quantidade | E9: Quantidade Referência | F9: Valor Referência | G9: Valor Custo | I9: Margem de Lucro | J9: Porcentagem | L9: DRE - Projeto | N9: Valor | O9: % do Preço | Q9: Valor | R9: % do Preço
B10: Registro | C10: Ovo | D10: 1 | E10: =IFERROR(VLOOKUP(C10,'Registro de Insumos'!D:G,3,FALSE),"") | F10: =IFERROR(VLOOKUP(C10,'Registro de Insumos'!D:G,4,FALSE),"") | G10: =IFERROR((F10/E10)*D10,"") | I10: Margem Desejada | J10: 0.1 | L10: Preço de Venda | N10: =J27 -> 0 | O10: =J14*J25/N10 -> #DIV/0! | Q10: 0.3 | R10: 0.3
E11: =IFERROR(VLOOKUP(C11,'Registro de Insumos'!D:G,3,FALSE),"") | F11: =IFERROR(VLOOKUP(C11,'Registro de Insumos'!D:G,4,FALSE),"") | G11: =IFERROR((F11/E11)*D11,"")
E12: =IFERROR(VLOOKUP(C12,'Registro de Insumos'!D:G,3,FALSE),"") | F12: =IFERROR(VLOOKUP(C12,'Registro de Insumos'!D:G,4,FALSE),"") | G12: =IFERROR((F12/E12)*D12,"") | I12: Unidades desse Lote | J12: Quantidade Unitária | L12: =#REF! -> #REF! | N12: =IFERROR(O12*$N$10,"") -> 0 | O12: =IFERROR(VLOOKUP(L12,'Gastos Variáveis'!D:E,2,FALSE),"") | Q12: =#REF! -> #REF! | R12: =#REF! -> #REF!
E13: =IFERROR(VLOOKUP(C13,'Registro de Insumos'!D:G,3,FALSE),"") | F13: =IFERROR(VLOOKUP(C13,'Registro de Insumos'!D:G,4,FALSE),"") | G13: =IFERROR((F13/E13)*D13,"") | I13: Quantidade Produzida | J13: 10 | L13: =#REF! -> #REF! | N13: =IFERROR(O13*$N$10,"") -> 0 | O13: =IFERROR(VLOOKUP(L13,'Gastos Variáveis'!D:E,2,FALSE),"") | Q13: =#REF! -> #REF! | R13: =#REF! -> #REF!
E14: =IFERROR(VLOOKUP(C14,'Registro de Insumos'!D:G,3,FALSE),"") | F14: =IFERROR(VLOOKUP(C14,'Registro de Insumos'!D:G,4,FALSE),"") | G14: =IFERROR((F14/E14)*D14,"") | I14: Custo Unitário | J14: =(SUM(G10:G9999))/J13 -> 0 | L14: =#REF! -> #REF! | N14: =IFERROR(O14*$N$10,"") -> 0 | O14: =IFERROR(VLOOKUP(L14,'Gastos Variáveis'!D:E,2,FALSE),"") | Q14: =#REF! -> #REF! | R14: =#REF! -> #REF!
E15: =IFERROR(VLOOKUP(C15,'Registro de Insumos'!D:G,3,FALSE),"") | F15: =IFERROR(VLOOKUP(C15,'Registro de Insumos'!D:G,4,FALSE),"") | G15: =IFERROR((F15/E15)*D15,"") | L15: ='Gastos Variáveis'!D14 -> Impostos | N15: =IFERROR(O15*$N$10,"") -> 0 | O15: =IFERROR(VLOOKUP(L15,'Gastos Variáveis'!D:E,2,FALSE),"") -> 0.0094 | Q15: ='Gastos Variáveis'!I14 | R15: ='Gastos Variáveis'!J14
E16: =IFERROR(VLOOKUP(C16,'Registro de Insumos'!D:G,3,FALSE),"") | F16: =IFERROR(VLOOKUP(C16,'Registro de Insumos'!D:G,4,FALSE),"") | G16: =IFERROR((F16/E16)*D16,"") | N16: =IFERROR(O16*$N$10,"") -> 0 | O16: =IFERROR(VLOOKUP(L16,'Gastos Variáveis'!D:E,2,FALSE),"") | Q16: ='Gastos Variáveis'!I15 | R16: ='Gastos Variáveis'!J15
E17: =IFERROR(VLOOKUP(C17,'Registro de Insumos'!D:G,3,FALSE),"") | F17: =IFERROR(VLOOKUP(C17,'Registro de Insumos'!D:G,4,FALSE),"") | G17: =IFERROR((F17/E17)*D17,"") | I17: Precificação do Produto | L17: ='Gastos Variáveis'!D16 | N17: =IFERROR(O17*$N$10,"") -> 0 | O17: =IFERROR(VLOOKUP(L17,'Gastos Variáveis'!D:E,2,FALSE),"") | Q17: ='Gastos Variáveis'!I16 | R17: ='Gastos Variáveis'!J16
E18: =IFERROR(VLOOKUP(C18,'Registro de Insumos'!D:G,3,FALSE),"") | F18: =IFERROR(VLOOKUP(C18,'Registro de Insumos'!D:G,4,FALSE),"") | G18: =IFERROR((F18/E18)*D18,"") | H18: Horas trabalhadas p/ mês | L18: ='Gastos Variáveis'!D17 | N18: =IFERROR(O18*$N$10,"") -> 0 | O18: =IFERROR(VLOOKUP(L18,'Gastos Variáveis'!D:E,2,FALSE),"") | Q18: ='Gastos Variáveis'!I17 | R18: ='Gastos Variáveis'!J17
E19: =IFERROR(VLOOKUP(C19,'Registro de Insumos'!D:G,3,FALSE),"") | F19: =IFERROR(VLOOKUP(C19,'Registro de Insumos'!D:G,4,FALSE),"") | G19: =IFERROR((F19/E19)*D19,"") | H19: 160 | I19: Informações | J19: Valor | L19: ='Gastos Variáveis'!D18 | N19: =IFERROR(O19*$N$10,"") -> 0 | O19: =IFERROR(VLOOKUP(L19,'Gastos Variáveis'!D:E,2,FALSE),"") | Q19: ='Gastos Variáveis'!I18 | R19: ='Gastos Variáveis'!J18
E20: =IFERROR(VLOOKUP(C20,'Registro de Insumos'!D:G,3,FALSE),"") | F20: =IFERROR(VLOOKUP(C20,'Registro de Insumos'!D:G,4,FALSE),"") | G20: =IFERROR((F20/E20)*D20,"") | H20: 176 | I20: Custo Fixo | J20: ='Gastos Fixos'!H11 -> 0.20082555 | L20: Total Custos Variáveis | N20: 0.3 | O20: 0.3 | Q20: 0.3 | R20: 0.3
E21: =IFERROR(VLOOKUP(C21,'Registro de Insumos'!D:G,3,FALSE),"") | F21: =IFERROR(VLOOKUP(C21,'Registro de Insumos'!D:G,4,FALSE),"") | G21: =IFERROR((F21/E21)*D21,"") | H21: 176 | I21: Custo Variável | J21: ='Gastos Variáveis'!H9 -> 0.0094 | L21: Total Custos Fixos | N21: 0.3 | O21: 0.3 | Q21: 0.3 | R21: 0.3
E22: =IFERROR(VLOOKUP(C22,'Registro de Insumos'!D:G,3,FALSE),"") | F22: =IFERROR(VLOOKUP(C22,'Registro de Insumos'!D:G,4,FALSE),"") | G22: =IFERROR((F22/E22)*D22,"") | I22: Margem | J22: =J10 -> 0.1 | L22: Custo do Produto | N22: 0.3 | O22: 0.3 | Q22: 0.3 | R22: 0.3
E23: =IFERROR(VLOOKUP(C23,'Registro de Insumos'!D:G,3,FALSE),"") | F23: =IFERROR(VLOOKUP(C23,'Registro de Insumos'!D:G,4,FALSE),"") | G23: =IFERROR((F23/E23)*D23,"") | I23: Salários | J23: ='Base de Salários'!J14 -> 0.0084433977 | L23: Total de Custos | N23: 0.3 | O23: 0.3 | Q23: 0.3 | R23: 0.3
E24: =IFERROR(VLOOKUP(C24,'Registro de Insumos'!D:G,3,FALSE),"") | F24: =IFERROR(VLOOKUP(C24,'Registro de Insumos'!D:G,4,FALSE),"") | G24: =IFERROR((F24/E24)*D24,"") | I24: Soma | J24: =SUM(J20:J23) -> 0.31866895
E25: =IFERROR(VLOOKUP(C25,'Registro de Insumos'!D:G,3,FALSE),"") | F25: =IFERROR(VLOOKUP(C25,'Registro de Insumos'!D:G,4,FALSE),"") | G25: =IFERROR((F25/E25)*D25,"") | I25: Markup | J25: =1/(1-(J20+J21+J22+J23)) -> 1.4677153 | L25: Margem de Lucro | N25: 0.3 | O25: 0.3 | Q25: 0.3 | R25: 0.3
E26: =IFERROR(VLOOKUP(C26,'Registro de Insumos'!D:G,3,FALSE),"") | F26: =IFERROR(VLOOKUP(C26,'Registro de Insumos'!D:G,4,FALSE),"") | G26: =IFERROR((F26/E26)*D26,"")
E27: =IFERROR(VLOOKUP(C27,'Registro de Insumos'!D:G,3,FALSE),"") | F27: =IFERROR(VLOOKUP(C27,'Registro de Insumos'!D:G,4,FALSE),"") | G27: =IFERROR((F27/E27)*D27,"") | I27: Preço de Venda | J27: =J14*J25 -> 0
E28: =IFERROR(VLOOKUP(C28,'Registro de Insumos'!D:G,3,FALSE),"") | F28: =IFERROR(VLOOKUP(C28,'Registro de Insumos'!D:G,4,FALSE),"") | G28: =IFERROR((F28/E28)*D28,"")
E29: =IFERROR(VLOOKUP(C29,'Registro de Insumos'!D:G,3,FALSE),"") | F29: =IFERROR(VLOOKUP(C29,'Registro de Insumos'!D:G,4,FALSE),"") | G29: =IFERROR((F29/E29)*D29,"")
E30: =IFERROR(VLOOKUP(C30,'Registro de Insumos'!D:G,3,FALSE),"") | F30: =IFERROR(VLOOKUP(C30,'Registro de Insumos'!D:G,4,FALSE),"") | G30: =IFERROR((F30/E30)*D30,"")
E31: =IFERROR(VLOOKUP(C31,'Registro de Insumos'!D:G,3,FALSE),"") | F31: =IFERROR(VLOOKUP(C31,'Registro de Insumos'!D:G,4,FALSE),"") | G31: =IFERROR((F31/E31)*D31,"")
E32: =IFERROR(VLOOKUP(C32,'Registro de Insumos'!D:G,3,FALSE),"") | F32: =IFERROR(VLOOKUP(C32,'Registro de Insumos'!D:G,4,FALSE),"") | G32: =IFERROR((F32/E32)*D32,"")
E33: =IFERROR(VLOOKUP(C33,'Registro de Insumos'!D:G,3,FALSE),"") | F33: =IFERROR(VLOOKUP(C33,'Registro de Insumos'!D:G,4,FALSE),"") | G33: =IFERROR((F33/E33)*D33,"")
E34: =IFERROR(VLOOKUP(C34,'Registro de Insumos'!D:G,3,FALSE),"") | F34: =IFERROR(VLOOKUP(C34,'Registro de Insumos'!D:G,4,FALSE),"") | G34: =IFERROR((F34/E34)*D34,"")
E35: =IFERROR(VLOOKUP(C35,'Registro de Insumos'!D:G,3,FALSE),"") | F35: =IFERROR(VLOOKUP(C35,'Registro de Insumos'!D:G,4,FALSE),"") | G35: =IFERROR((F35/E35)*D35,"")
E36: =IFERROR(VLOOKUP(C36,'Registro de Insumos'!D:G,3,FALSE),"") | F36: =IFERROR(VLOOKUP(C36,'Registro de Insumos'!D:G,4,FALSE),"") | G36: =IFERROR((F36/E36)*D36,"")
E37: =IFERROR(VLOOKUP(C37,'Registro de Insumos'!D:G,3,FALSE),"") | F37: =IFERROR(VLOOKUP(C37,'Registro de Insumos'!D:G,4,FALSE),"") | G37: =IFERROR((F37/E37)*D37,"")
E38: =IFERROR(VLOOKUP(C38,'Registro de Insumos'!D:G,3,FALSE),"") | F38: =IFERROR(VLOOKUP(C38,'Registro de Insumos'!D:G,4,FALSE),"") | G38: =IFERROR((F38/E38)*D38,"")
E39: =IFERROR(VLOOKUP(C39,'Registro de Insumos'!D:G,3,FALSE),"") | F39: =IFERROR(VLOOKUP(C39,'Registro de Insumos'!D:G,4,FALSE),"") | G39: =IFERROR((F39/E39)*D39,"")
... E101: =IFERROR(VLOOKUP(C101,'Registro de Insumos'!D:G,3,FALSE),"") | F101: =IFERROR(VLOOKUP(C101,'Registro de Insumos'!D:G,4,FALSE),"") | G101: =IFERROR((F101/E101)*D101,"")

Sheet Síntese de Precificação
B1: Síntese de Precificação
B7: Código do Produto | C7: Nome do Item | D7: Custo Total | E7: Preço Sugerido | F7: Preço praticado | G7: MCu ($) | H7: MCu (%) | I7: Markup | J7: Margem de Lucro | K7: Preço de venda | L7: Preço de venda | M7: Preço de venda | N7: Diferença de preço
B8: {=UNIQUE('Precificação Produto | Custo Co'!C10:C999)} | C8: =IFERROR(VLOOKUP(B8, 'Registro de Fichas Técnicas'!$B$40:$C$993, 2, FALSE), "") | D8: =IF(B8="","",E8*(1-'Precificação Produto | Custo Co'!$K$10)) | E8: ='Precificação Produto | Custo Co'!K27 -> 0 | F8: 58.207948 | G8: =IF(B8="","",IF($F8="",$E8,$F8) - SUMIFS('Precificação Produto | Custo Co'!$H:$H,'Precificação Produto | Custo Co'!$C:$C,$B8) * (1+SUM('Gastos Variáveis'!$E:$E))) | H8: =IFERROR(IF($F8="",$G8/$E8,$G8/$F8),) -> 0 | I8: =IFERROR(IF($F8="",$E8,$F8) / (SUMIFS('Precificação Produto | Custo Co'!$H:$H,'Precificação Produto | Custo Co'!$C:$C,$B8)/'Precificação Produto | Custo Co'!K13),"") | J8: =IFERROR(IF($F8="",($E8-$D8)/$E8,($F8-$D8)/$F8),) -> 1 | K8: =IF($F8="",$E8,$F8) -> 58.207948 | L8: =IF($F8="",$E8,$F8) -> 58.207948 | M8: =IF($F8="",$E8,$F8) -> 58.207948 | N8: =IF(B8="","",(F8-E8)/F8)
C9: =IFERROR(VLOOKUP(B9, 'Registro de Fichas Técnicas'!$B$40:$C$993, 2, FALSE), "") | D9: =IF(B9="","",E9*(1-'Precificação Produto | Custo Co'!$K$10)) | E9: =IF(B9="","",SUMIF('Precificação Produto | Custo Co'!$C$10:$C$999,B9, 'Precificação Produto | Custo Co'!$H$10:$H$999)*'Precificação Produto | Custo Co'!$K$25) | G9: =IF(B9="","",IF($F9="",$E9,$F9) - SUMIFS('Precificação Produto | Custo Co'!$H:$H,'Precificação Produto | Custo Co'!$C:$C,$B9) * (1+SUM('Gastos Variáveis'!$E:$E))) | H9: =IFERROR(IF($F9="",$G9/$E9,$G9/$F9),) | I9: =IFERROR(IF($F9="",$E9,$F9) / (SUMIFS('Precificação Produto | Custo Co'!$H:$H,'Precificação Produto | Custo Co'!$C:$C,$B9)*(1+SUM('Gastos Variáveis'!$E:$E))),) | J9: =IFERROR(IF($F9="",($E9-$D9)/$E9,($F9-$D9)/$F9),) | K9: =IF($F9="",$E9,$F9) | L9: =IF($F9="",$E9,$F9) | M9: =IF($F9="",$E9,$F9) | N9: =IF(B9="","",(F9-E9)/F9)
C10: =IFERROR(VLOOKUP(B10, 'Registro de Fichas Técnicas'!$B$40:$C$993, 2, FALSE), "") | D10: =IF(B10="","",E10*(1-'Precificação Produto | Custo Co'!$K$10)) | E10: =IF(B10="","",SUMIF('Precificação Produto | Custo Co'!$C$10:$C$999,B10, 'Precificação Produto | Custo Co'!$H$10:$H$999)*'Precificação Produto | Custo Co'!$K$25) | G10: =IF(B10="","",IF($F10="",$E10,$F10) - SUMIFS('Precificação Produto | Custo Co'!$H:$H,'Precificação Produto | Custo Co'!$C:$C,$B10) * (1+SUM('Gastos Variáveis'!$E:$E))) | H10: =IFERROR(IF($F10="",$G10/$E10,$G10/$F10),) | I10: =IFERROR(IF($F10="",$E10,$F10) / (SUMIFS('Precificação Produto | Custo Co'!$H:$H,'Precificação Produto | Custo Co'!$C:$C,$B10)*(1+SUM('Gastos Variáveis'!$E:$E))),) | J10: =IFERROR(IF($F10="",($E10-$D10)/$E10,($F10-$D10)/$F10),) | K10: =IF($F10="",$E10,$F10) | L10: =IF($F10="",$E10,$F10) | M10: =IF($F10="",$E10,$F10) | N10: =IF(B10="","",(F10-E10)/F10)
C11: =IFERROR(VLOOKUP(B11, 'Registro de Fichas Técnicas'!$B$40:$C$993, 2, FALSE), "") | D11: =IF(B11="","",E11*(1-'Precificação Produto | Custo Co'!$K$10)) | E11: =IF(B11="","",SUMIF('Precificação Produto | Custo Co'!$C$10:$C$999,B11, 'Precificação Produto | Custo Co'!$H$10:$H$999)*'Precificação Produto | Custo Co'!$K$25) | G11: =IF(B11="","",IF($F11="",$E11,$F11) - SUMIFS('Precificação Produto | Custo Co'!$H:$H,'Precificação Produto | Custo Co'!$C:$C,$B11) * (1+SUM('Gastos Variáveis'!$E:$E))) | H11: =IFERROR(IF($F11="",$G11/$E11,$G11/$F11),) | I11: =IFERROR(IF($F11="",$E11,$F11) / (SUMIFS('Precificação Produto | Custo Co'!$H:$H,'Precificação Produto | Custo Co'!$C:$C,$B11)*(1+SUM('Gastos Variáveis'!$E:$E))),) | J11: =IFERROR(IF($F11="",($E11-$D11)/$E11,($F11-$D11)/$F11),) | K11: =IF($F11="",$E11,$F11) | L11: =IF($F11="",$E11,$F11) | M11: =IF($F11="",$E11,$F11) | N11: =IF(B11="","",(F11-E11)/F11)
C12: =IFERROR(VLOOKUP(B12, 'Registro de Fichas Técnicas'!$B$40:$C$993, 2, FALSE), "") | D12: =IF(B12="","",E12*(1-'Precificação Produto | Custo Co'!$K$10)) | E12: =IF(B12="","",SUMIF('Precificação Produto | Custo Co'!$C$10:$C$999,B12, 'Precificação Produto | Custo Co'!$H$10:$H$999)*'Precificação Produto | Custo Co'!$K$25) | G12: =IF(B12="","",IF($F12="",$E12,$F12) - SUMIFS('Precificação Produto | Custo Co'!$H:$H,'Precificação Produto | Custo Co'!$C:$C,$B12) * (1+SUM('Gastos Variáveis'!$E:$E))) | H12: =IFERROR(IF($F12="",$G12/$E12,$G12/$F12),) | I12: =IFERROR(IF($F12="",$E12,$F12) / (SUMIFS('Precificação Produto | Custo Co'!$H:$H,'Precificação Produto | Custo Co'!$C:$C,$B12)*(1+SUM('Gastos Variáveis'!$E:$E))),) | J12: =IFERROR(IF($F12="",($E12-$D12)/$E12,($F12-$D12)/$F12),) | K12: =IF($F12="",$E12,$F12) | L12: =IF($F12="",$E12,$F12) | M12: =IF($F12="",$E12,$F12) | N12: =IF(B12="","",(F12-E12)/F12)
C13: =IFERROR(VLOOKUP(B13, 'Registro de Fichas Técnicas'!$B$40:$C$993, 2, FALSE), "") | D13: =IF(B13="","",E13*(1-'Precificação Produto | Custo Co'!$K$10)) | E13: =IF(B13="","",SUMIF('Precificação Produto | Custo Co'!$C$10:$C$999,B13, 'Precificação Produto | Custo Co'!$H$10:$H$999)*'Precificação Produto | Custo Co'!$K$25) | G13: =IF(B13="","",IF($F13="",$E13,$F13) - SUMIFS('Precificação Produto | Custo Co'!$H:$H,'Precificação Produto | Custo Co'!$C:$C,$B13) * (1+SUM('Gastos Variáveis'!$E:$E))) | H13: =IFERROR(IF($F13="",$G13/$E13,$G13/$F13),) | I13: =IFERROR(IF($F13="",$E13,$F13) / (SUMIFS('Precificação Produto | Custo Co'!$H:$H,'Precificação Produto | Custo Co'!$C:$C,$B13)*(1+SUM('Gastos Variáveis'!$E:$E))),) | J13: =IFERROR(IF($F13="",($E13-$D13)/$E13,($F13-$D13)/$F13),) | K13: =IF($F13="",$E13,$F13) | L13: =IF($F13="",$E13,$F13) | M13: =IF($F13="",$E13,$F13) | N13: =IF(B13="","",(F13-E13)/F13)
C14: =IFERROR(VLOOKUP(B14, 'Registro de Fichas Técnicas'!$B$40:$C$993, 2, FALSE), "") | D14: =IF(B14="","",E14*(1-'Precificação Produto | Custo Co'!$K$10)) | E14: =IF(B14="","",SUMIF('Precificação Produto | Custo Co'!$C$10:$C$999,B14, 'Precificação Produto | Custo Co'!$H$10:$H$999)*'Precificação Produto | Custo Co'!$K$25) | G14: =IF(B14="","",IF($F14="",$E14,$F14) - SUMIFS('Precificação Produto | Custo Co'!$H:$H,'Precificação Produto | Custo Co'!$C:$C,$B14) * (1+SUM('Gastos Variáveis'!$E:$E))) | H14: =IFERROR(IF($F14="",$G14/$E14,$G14/$F14),) | I14: =IFERROR(IF($F14="",$E14,$F14) / (SUMIFS('Precificação Produto | Custo Co'!$H:$H,'Precificação Produto | Custo Co'!$C:$C,$B14)*(1+SUM('Gastos Variáveis'!$E:$E))),) | J14: =IFERROR(IF($F14="",($E14-$D14)/$E14,($F14-$D14)/$F14),) | K14: =IF($F14="",$E14,$F14) | L14: =IF($F14="",$E14,$F14) | M14: =IF($F14="",$E14,$F14) | N14: =IF(B14="","",(F14-E14)/F14)
C15: =IFERROR(VLOOKUP(B15, 'Registro de Fichas Técnicas'!$B$40:$C$993, 2, FALSE), "") | D15: =IF(B15="","",E15*(1-'Precificação Produto | Custo Co'!$K$10)) | E15: =IF(B15="","",SUMIF('Precificação Produto | Custo Co'!$C$10:$C$999,B15, 'Precificação Produto | Custo Co'!$H$10:$H$999)*'Precificação Produto | Custo Co'!$K$25) | G15: =IF(B15="","",IF($F15="",$E15,$F15) - SUMIFS('Precificação Produto | Custo Co'!$H:$H,'Precificação Produto | Custo Co'!$C:$C,$B15) * (1+SUM('Gastos Variáveis'!$E:$E))) | H15: =IFERROR(IF($F15="",$G15/$E15,$G15/$F15),) | I15: =IFERROR(IF($F15="",$E15,$F15) / (SUMIFS('Precificação Produto | Custo Co'!$H:$H,'Precificação Produto | Custo Co'!$C:$C,$B15)*(1+SUM('Gastos Variáveis'!$E:$E))),) | J15: =IFERROR(IF($F15="",($E15-$D15)/$E15,($F15-$D15)/$F15),) | K15: =IF($F15="",$E15,$F15) | L15: =IF($F15="",$E15,$F15) | M15: =IF($F15="",$E15,$F15) | N15: =IF(B15="","",(F15-E15)/F15)
C16: =IFERROR(VLOOKUP(B16, 'Registro de Fichas Técnicas'!$B$40:$C$993, 2, FALSE), "") | D16: =IF(B16="","",E16*(1-'Precificação Produto | Custo Co'!$K$10)) | E16: =IF(B16="","",SUMIF('Precificação Produto | Custo Co'!$C$10:$C$999,B16, 'Precificação Produto | Custo Co'!$H$10:$H$999)*'Precificação Produto | Custo Co'!$K$25) | G16: =IF(B16="","",IF($F16="",$E16,$F16) - SUMIFS('Precificação Produto | Custo Co'!$H:$H,'Precificação Produto | Custo Co'!$C:$C,$B16) * (1+SUM('Gastos Variáveis'!$E:$E))) | H16: =IFERROR(IF($F16="",$G16/$E16,$G16/$F16),) | I16: =IFERROR(IF($F16="",$E16,$F16) / (SUMIFS('Precificação Produto | Custo Co'!$H:$H,'Precificação Produto | Custo Co'!$C:$C,$B16)*(1+SUM('Gastos Variáveis'!$E:$E))),) | J16: =IFERROR(IF($F16="",($E16-$D16)/$E16,($F16-$D16)/$F16),) | K16: =IF($F16="",$E16,$F16) | L16: =IF($F16="",$E16,$F16) | M16: =IF($F16="",$E16,$F16) | N16: =IF(B16="","",(F16-E16)/F16)
C17: =IFERROR(VLOOKUP(B17, 'Registro de Fichas Técnicas'!$B$40:$C$993, 2, FALSE), "") | D17: =IF(B17="","",E17*(1-'Precificação Produto | Custo Co'!$K$10)) | E17: =IF(B17="","",SUMIF('Precificação Produto | Custo Co'!$C$10:$C$999,B17, 'Precificação Produto | Custo Co'!$H$10:$H$999)*'Precificação Produto | Custo Co'!$K$25) | G17: =IF(B17="","",IF($F17="",$E17,$F17) - SUMIFS('Precificação Produto | Custo Co'!$H:$H,'Precificação Produto | Custo Co'!$C:$C,$B17) * (1+SUM('Gastos Variáveis'!$E:$E))) | H17: =IFERROR(IF($F17="",$G17/$E17,$G17/$F17),) | I17: =IFERROR(IF($F17="",$E17,$F17) / (SUMIFS('Precificação Produto | Custo Co'!$H:$H,'Precificação Produto | Custo Co'!$C:$C,$B17)*(1+SUM('Gastos Variáveis'!$E:$E))),) | J17: =IFERROR(IF($F17="",($E17-$D17)/$E17,($F17-$D17)/$F17),) | K17: =IF($F17="",$E17,$F17) | L17: =IF($F17="",$E17,$F17) | M17: =IF($F17="",$E17,$F17) | N17: =IF(B17="","",(F17-E17)/F17)
C18: =IFERROR(VLOOKUP(B18, 'Registro de Fichas Técnicas'!$B$40:$C$993, 2, FALSE), "") | D18: =IF(B18="","",E18*(1-'Precificação Produto | Custo Co'!$K$10)) | E18: =IF(B18="","",SUMIF('Precificação Produto | Custo Co'!$C$10:$C$999,B18, 'Precificação Produto | Custo Co'!$H$10:$H$999)*'Precificação Produto | Custo Co'!$K$25) | G18: =IF(B18="","",IF($F18="",$E18,$F18) - SUMIFS('Precificação Produto | Custo Co'!$H:$H,'Precificação Produto | Custo Co'!$C:$C,$B18) * (1+SUM('Gastos Variáveis'!$E:$E))) | H18: =IFERROR(IF($F18="",$G18/$E18,$G18/$F18),) | I18: =IFERROR(IF($F18="",$E18,$F18) / (SUMIFS('Precificação Produto | Custo Co'!$H:$H,'Precificação Produto | Custo Co'!$C:$C,$B18)*(1+SUM('Gastos Variáveis'!$E:$E))),) | J18: =IFERROR(IF($F18="",($E18-$D18)/$E18,($F18-$D18)/$F18),) | K18: =IF($F18="",$E18,$F18) | L18: =IF($F18="",$E18,$F18) | M18: =IF($F18="",$E18,$F18) | N18: =IF(B18="","",(F18-E18)/F18)
C19: =IFERROR(VLOOKUP(B19, 'Registro de Fichas Técnicas'!$B$40:$C$993, 2, FALSE), "") | D19: =IF(B19="","",E19*(1-'Precificação Produto | Custo Co'!$K$10)) | E19: =IF(B19="","",SUMIF('Precificação Produto | Custo Co'!$C$10:$C$999,B19, 'Precificação Produto | Custo Co'!$H$10:$H$999)*'Precificação Produto | Custo Co'!$K$25) | G19: =IF(B19="","",IF($F19="",$E19,$F19) - SUMIFS('Precificação Produto | Custo Co'!$H:$H,'Precificação Produto | Custo Co'!$C:$C,$B19) * (1+SUM('Gastos Variáveis'!$E:$E))) | H19: =IFERROR(IF($F19="",$G19/$E19,$G19/$F19),) | I19: =IFERROR(IF($F19="",$E19,$F19) / (SUMIFS('Precificação Produto | Custo Co'!$H:$H,'Precificação Produto | Custo Co'!$C:$C,$B19)*(1+SUM('Gastos Variáveis'!$E:$E))),) | J19: =IFERROR(IF($F19="",($E19-$D19)/$E19,($F19-$D19)/$F19),) | K19: =IF($F19="",$E19,$F19) | L19: =IF($F19="",$E19,$F19) | M19: =IF($F19="",$E19,$F19) | N19: =IF(B19="","",(F19-E19)/F19)
C20: =IFERROR(VLOOKUP(B20, 'Registro de Fichas Técnicas'!$B$40:$C$993, 2, FALSE), "") | D20: =IF(B20="","",E20*(1-'Precificação Produto | Custo Co'!$K$10)) | E20: =IF(B20="","",SUMIF('Precificação Produto | Custo Co'!$C$10:$C$999,B20, 'Precificação Produto | Custo Co'!$H$10:$H$999)*'Precificação Produto | Custo Co'!$K$25) | G20: =IF(B20="","",IF($F20="",$E20,$F20) - SUMIFS('Precificação Produto | Custo Co'!$H:$H,'Precificação Produto | Custo Co'!$C:$C,$B20) * (1+SUM('Gastos Variáveis'!$E:$E))) | H20: =IFERROR(IF($F20="",$G20/$E20,$G20/$F20),) | I20: =IFERROR(IF($F20="",$E20,$F20) / (SUMIFS('Precificação Produto | Custo Co'!$H:$H,'Precificação Produto | Custo Co'!$C:$C,$B20)*(1+SUM('Gastos Variáveis'!$E:$E))),) | J20: =IFERROR(IF($F20="",($E20-$D20)/$E20,($F20-$D20)/$F20),) | K20: =IF($F20="",$E20,$F20) | L20: =IF($F20="",$E20,$F20) | M20: =IF($F20="",$E20,$F20) | N20: =IF(B20="","",(F20-E20)/F20)
... C333: =IFERROR(VLOOKUP(B333, 'Registro de Fichas Técnicas'!$B$40:$C$993, 2, FALSE), "") | D333: =IF(B333="","",E333*(1-'Precificação Produto | Custo Co'!$K$10)) | E333: =IF(B333="","",SUMIF('Precificação Produto | Custo Co'!$C$10:$C$999,B333, 'Precificação Produto | Custo Co'!$H$10:$H$999)*'Precificação Produto | Custo Co'!$K$25) | G333: =IF(B333="","",IF($F333="",$E333,$F333) - SUMIFS('Precificação Produto | Custo Co'!$H:$H,'Precificação Produto | Custo Co'!$C:$C,$B333) * (1+SUM('Gastos Variáveis'!$E:$E))) | H333: =IFERROR(IF($F333="",$G333/$E333,$G333/$F333),) | I333: =IFERROR(IF($F333="",$E333,$F333) / (SUMIFS('Precificação Produto | Custo Co'!$H:$H,'Precificação Produto | Custo Co'!$C:$C,$B333)*(1+SUM('Gastos Variáveis'!$E:$E))),) | J333: =IFERROR(IF($F333="",($E333-$D333)/$E333,($F333-$D333)/$F333),) | K333: =IF($F333="",$E333,$F333) | L333: =IF($F333="",$E333,$F333) | M333: =IF($F333="",$E333,$F333) | N333: =IF(B333="","",(F333-E333)/F333)

Sheet Config_Areas
A1: Área | B1: Cargo
A2: Pintura | B2: Ajudante Geral - Ricardo
A3: Limpeza | B3: Ajudante Geral - Tierry
A4: Engenharia | B4: Almoxarifado
A5: Transporte | B5: Analista de RH
A6: Serralheria | B6: Assistente Administrativo
A7: Montagem | B7: Auxiliar de Eletricista - Alisson
A8: Almoxarifado | B8: Auxiliar de Eletricista - Bruno
B9: Auxiliar de Eletricista - Manoel
B10: Auxiliar de Limpeza
B11: Eletricista - Antonio
B12: Eletricista - Joeilson
B13: Eletricista - Wandercy
B14: Encarregado de Eletrica - Gildemar
B15: Encarregado de Elétrica - Wesley
B16: Encarregado Geral
B17: Mestre Serralheiro
B18: Motorista
B19: Pintor
B20: Serralheiro

Sheet Indicadores
B1: Indicadores
B7: 2024
C12: Ano e Mês | D12: Entrada | E12: Saída | F12: Lucro Líquido | G12: Fluxo de Caixa Acumulado | H12: Custos Fixos | I12: Custos Variáveis | J12: Despesas | K12: Investimentos | L12: Inadimplência | M12: Runway | N12: Margem de Contribuição | O12: Breakeven | P12: Margem Líquida | Q12: Faturamento
A13: =$B$7 -> 2024 | B13: 1 | C13: =DATE(A13,B13,1) -> 45292 | D13: {=IFERROR(XLOOKUP($B$7&$C13,$B$26:$B63&$D$26:$D63,E$26:E63),"")} | E13: {=IFERROR(XLOOKUP($B$7&$C13,$B$26:$B63&$D$26:$D63,F$26:F63),"")} | F13: {=IFERROR(XLOOKUP($B$7&$C13,$B$26:$B63&$D$26:$D63,G$26:G63),"")} | G13: {=IFERROR(XLOOKUP($B$7&$C13,$B$26:$B63&$D$26:$D63,H$26:H63),"")} | H13: {=IFERROR(XLOOKUP($B$7&$C13,$B$26:$B63&$D$26:$D63,I$26:I63),"")} | I13: {=IFERROR(XLOOKUP($B$7&$C13,$B$26:$B63&$D$26:$D63,J$26:J63),"")} | J13: {=IFERROR(XLOOKUP($B$7&$C13,$B$26:$B63&$D$26:$D63,K$26:K63),"")} | K13: {=IFERROR(XLOOKUP($B$7&$C13,$B$26:$B63&$D$26:$D63,L$26:L63),"")} | ... Q13: {=IFERROR(XLOOKUP($B$7&$C13,$B$26:$B63&$D$26:$D63,R$26:R63),"")}
A14: =$B$7 -> 2024 | B14: 2 | C14: =DATE(A14,B14,1) -> 45323 | D14: {=IFERROR(XLOOKUP($B$7&$C14,$B$26:$B63&$D$26:$D63,E$26:E63),"")} | E14: {=IFERROR(XLOOKUP($B$7&$C14,$B$26:$B63&$D$26:$D63,F$26:F63),"")} | F14: {=IFERROR(XLOOKUP($B$7&$C14,$B$26:$B63&$D$26:$D63,G$26:G63),"")} | G14: {=IFERROR(XLOOKUP($B$7&$C14,$B$26:$B63&$D$26:$D63,H$26:H63),"")} | H14: {=IFERROR(XLOOKUP($B$7&$C14,$B$26:$B63&$D$26:$D63,I$26:I63),"")} | I14: {=IFERROR(XLOOKUP($B$7&$C14,$B$26:$B63&$D$26:$D63,J$26:J63),"")} | J14: {=IFERROR(XLOOKUP($B$7&$C14,$B$26:$B63&$D$26:$D63,K$26:K63),"")} | K14: {=IFERROR(XLOOKUP($B$7&$C14,$B$26:$B63&$D$26:$D63,L$26:L63),"")} | ... Q14: {=IFERROR(XLOOKUP($B$7&$C14,$B$26:$B63&$D$26:$D63,R$26:R63),"")}
A15: =$B$7 -> 2024 | B15: 3 | C15: =DATE(A15,B15,1) -> 45352 | D15: {=IFERROR(XLOOKUP($B$7&$C15,$B$26:$B63&$D$26:$D63,E$26:E63),"")} | E15: {=IFERROR(XLOOKUP($B$7&$C15,$B$26:$B63&$D$26:$D63,F$26:F63),"")} | F15: {=IFERROR(XLOOKUP($B$7&$C15,$B$26:$B63&$D$26:$D63,G$26:G63),"")} | G15: {=IFERROR(XLOOKUP($B$7&$C15,$B$26:$B63&$D$26:$D63,H$26:H63),"")} | H15: {=IFERROR(XLOOKUP($B$7&$C15,$B$26:$B63&$D$26:$D63,I$26:I63),"")} | I15: {=IFERROR(XLOOKUP($B$7&$C15,$B$26:$B63&$D$26:$D63,J$26:J63),"")} | J15: {=IFERROR(XLOOKUP($B$7&$C15,$B$26:$B63&$D$26:$D63,K$26:K63),"")} | K15: {=IFERROR(XLOOKUP($B$7&$C15,$B$26:$B63&$D$26:$D63,L$26:L63),"")} | ... Q15: {=IFERROR(XLOOKUP($B$7&$C15,$B$26:$B63&$D$26:$D63,R$26:R63),"")}
A16: =$B$7 -> 2024 | B16: 4 | C16: =DATE(A16,B16,1) -> 45383 | D16: {=IFERROR(XLOOKUP($B$7&$C16,$B$26:$B63&$D$26:$D63,E$26:E63),"")} | E16: {=IFERROR(XLOOKUP($B$7&$C16,$B$26:$B63&$D$26:$D63,F$26:F63),"")} | F16: {=IFERROR(XLOOKUP($B$7&$C16,$B$26:$B63&$D$26:$D63,G$26:G63),"")} | G16: {=IFERROR(XLOOKUP($B$7&$C16,$B$26:$B63&$D$26:$D63,H$26:H63),"")} | H16: {=IFERROR(XLOOKUP($B$7&$C16,$B$26:$B63&$D$26:$D63,I$26:I63),"")} | I16: {=IFERROR(XLOOKUP($B$7&$C16,$B$26:$B63&$D$26:$D63,J$26:J63),"")} | J16: {=IFERROR(XLOOKUP($B$7&$C16,$B$26:$B63&$D$26:$D63,K$26:K63),"")} | K16: {=IFERROR(XLOOKUP($B$7&$C16,$B$26:$B63&$D$26:$D63,L$26:L63),"")} | ... Q16: {=IFERROR(XLOOKUP($B$7&$C16,$B$26:$B63&$D$26:$D63,R$26:R63),"")}
A17: =$B$7 -> 2024 | B17: 5 | C17: =DATE(A17,B17,1) -> 45413 | D17: {=IFERROR(XLOOKUP($B$7&$C17,$B$26:$B63&$D$26:$D63,E$26:E63),"")} | E17: {=IFERROR(XLOOKUP($B$7&$C17,$B$26:$B63&$D$26:$D63,F$26:F63),"")} | F17: {=IFERROR(XLOOKUP($B$7&$C17,$B$26:$B63&$D$26:$D63,G$26:G63),"")} | G17: {=IFERROR(XLOOKUP($B$7&$C17,$B$26:$B63&$D$26:$D63,H$26:H63),"")} | H17: {=IFERROR(XLOOKUP($B$7&$C17,$B$26:$B63&$D$26:$D63,I$26:I63),"")} | I17: {=IFERROR(XLOOKUP($B$7&$C17,$B$26:$B63&$D$26:$D63,J$26:J63),"")} | J17: {=IFERROR(XLOOKUP($B$7&$C17,$B$26:$B63&$D$26:$D63,K$26:K63),"")} | K17: {=IFERROR(XLOOKUP($B$7&$C17,$B$26:$B63&$D$26:$D63,L$26:L63),"")} | ... Q17: {=IFERROR(XLOOKUP($B$7&$C17,$B$26:$B63&$D$26:$D63,R$26:R63),"")}
A18: =$B$7 -> 2024 | B18: 6 | C18: =DATE(A18,B18,1) -> 45444 | D18: {=IFERROR(XLOOKUP($B$7&$C18,$B$26:$B63&$D$26:$D63,E$26:E63),"")} | E18: {=IFERROR(XLOOKUP($B$7&$C18,$B$26:$B63&$D$26:$D63,F$26:F63),"")} | F18: {=IFERROR(XLOOKUP($B$7&$C18,$B$26:$B63&$D$26:$D63,G$26:G63),"")} | G18: {=IFERROR(XLOOKUP($B$7&$C18,$B$26:$B63&$D$26:$D63,H$26:H63),"")} | H18: {=IFERROR(XLOOKUP($B$7&$C18,$B$26:$B63&$D$26:$D63,I$26:I63),"")} | I18: {=IFERROR(XLOOKUP($B$7&$C18,$B$26:$B63&$D$26:$D63,J$26:J63),"")} | J18: {=IFERROR(XLOOKUP($B$7&$C18,$B$26:$B63&$D$26:$D63,K$26:K63),"")} | K18: {=IFERROR(XLOOKUP($B$7&$C18,$B$26:$B63&$D$26:$D63,L$26:L63),"")} | ... Q18: {=IFERROR(XLOOKUP($B$7&$C18,$B$26:$B63&$D$26:$D63,R$26:R63),"")}
A19: =$B$7 -> 2024 | B19: 7 | C19: =DATE(A19,B19,1) -> 45474 | D19: {=IFERROR(XLOOKUP($B$7&$C19,$B$26:$B63&$D$26:$D63,E$26:E63),"")} | E19: {=IFERROR(XLOOKUP($B$7&$C19,$B$26:$B63&$D$26:$D63,F$26:F63),"")} | F19: {=IFERROR(XLOOKUP($B$7&$C19,$B$26:$B63&$D$26:$D63,G$26:G63),"")} | G19: {=IFERROR(XLOOKUP($B$7&$C19,$B$26:$B63&$D$26:$D63,H$26:H63),"")} | H19: {=IFERROR(XLOOKUP($B$7&$C19,$B$26:$B63&$D$26:$D63,I$26:I63),"")} | I19: {=IFERROR(XLOOKUP($B$7&$C19,$B$26:$B63&$D$26:$D63,J$26:J63),"")} | J19: {=IFERROR(XLOOKUP($B$7&$C19,$B$26:$B63&$D$26:$D63,K$26:K63),"")} | K19: {=IFERROR(XLOOKUP($B$7&$C19,$B$26:$B63&$D$26:$D63,L$26:L63),"")} | ... Q19: {=IFERROR(XLOOKUP($B$7&$C19,$B$26:$B63&$D$26:$D63,R$26:R63),"")}
A20: =$B$7 -> 2024 | B20: 8 | C20: =DATE(A20,B20,1) -> 45505 | D20: {=IFERROR(XLOOKUP($B$7&$C20,$B$26:$B63&$D$26:$D63,E$26:E63),"")} | E20: {=IFERROR(XLOOKUP($B$7&$C20,$B$26:$B63&$D$26:$D63,F$26:F63),"")} | F20: {=IFERROR(XLOOKUP($B$7&$C20,$B$26:$B63&$D$26:$D63,G$26:G63),"")} | G20: {=IFERROR(XLOOKUP($B$7&$C20,$B$26:$B63&$D$26:$D63,H$26:H63),"")} | H20: {=IFERROR(XLOOKUP($B$7&$C20,$B$26:$B63&$D$26:$D63,I$26:I63),"")} | I20: {=IFERROR(XLOOKUP($B$7&$C20,$B$26:$B63&$D$26:$D63,J$26:J63),"")} | J20: {=IFERROR(XLOOKUP($B$7&$C20,$B$26:$B63&$D$26:$D63,K$26:K63),"")} | K20: {=IFERROR(XLOOKUP($B$7&$C20,$B$26:$B63&$D$26:$D63,L$26:L63),"")} | ... Q20: {=IFERROR(XLOOKUP($B$7&$C20,$B$26:$B63&$D$26:$D63,R$26:R63),"")}
A21: =$B$7 -> 2024 | B21: 9 | C21: =DATE(A21,B21,1) -> 45536 | D21: {=IFERROR(XLOOKUP($B$7&$C21,$B$26:$B63&$D$26:$D63,E$26:E63),"")} | E21: {=IFERROR(XLOOKUP($B$7&$C21,$B$26:$B63&$D$26:$D63,F$26:F63),"")} | F21: {=IFERROR(XLOOKUP($B$7&$C21,$B$26:$B63&$D$26:$D63,G$26:G63),"")} | G21: {=IFERROR(XLOOKUP($B$7&$C21,$B$26:$B63&$D$26:$D63,H$26:H63),"")} | H21: {=IFERROR(XLOOKUP($B$7&$C21,$B$26:$B63&$D$26:$D63,I$26:I63),"")} | I21: {=IFERROR(XLOOKUP($B$7&$C21,$B$26:$B63&$D$26:$D63,J$26:J63),"")} | J21: {=IFERROR(XLOOKUP($B$7&$C21,$B$26:$B63&$D$26:$D63,K$26:K63),"")} | K21: {=IFERROR(XLOOKUP($B$7&$C21,$B$26:$B63&$D$26:$D63,L$26:L63),"")} | ... Q21: {=IFERROR(XLOOKUP($B$7&$C21,$B$26:$B63&$D$26:$D63,R$26:R63),"")}
A22: =$B$7 -> 2024 | B22: 10 | C22: =DATE(A22,B22,1) -> 45566 | D22: {=IFERROR(XLOOKUP($B$7&$C22,$B$26:$B63&$D$26:$D63,E$26:E63),"")} | E22: {=IFERROR(XLOOKUP($B$7&$C22,$B$26:$B63&$D$26:$D63,F$26:F63),"")} | F22: {=IFERROR(XLOOKUP($B$7&$C22,$B$26:$B63&$D$26:$D63,G$26:G63),"")} | G22: {=IFERROR(XLOOKUP($B$7&$C22,$B$26:$B63&$D$26:$D63,H$26:H63),"")} | H22: {=IFERROR(XLOOKUP($B$7&$C22,$B$26:$B63&$D$26:$D63,I$26:I63),"")} | I22: {=IFERROR(XLOOKUP($B$7&$C22,$B$26:$B63&$D$26:$D63,J$26:J63),"")} | J22: {=IFERROR(XLOOKUP($B$7&$C22,$B$26:$B63&$D$26:$D63,K$26:K63),"")} | K22: {=IFERROR(XLOOKUP($B$7&$C22,$B$26:$B63&$D$26:$D63,L$26:L63),"")} | ... Q22: {=IFERROR(XLOOKUP($B$7&$C22,$B$26:$B63&$D$26:$D63,R$26:R63),"")}
A23: =$B$7 -> 2024 | B23: 11 | C23: =DATE(A23,B23,1) -> 45597 | D23: {=IFERROR(XLOOKUP($B$7&$C23,$B$26:$B63&$D$26:$D63,E$26:E63),"")} | E23: {=IFERROR(XLOOKUP($B$7&$C23,$B$26:$B63&$D$26:$D63,F$26:F63),"")} | F23: {=IFERROR(XLOOKUP($B$7&$C23,$B$26:$B63&$D$26:$D63,G$26:G63),"")} | G23: {=IFERROR(XLOOKUP($B$7&$C23,$B$26:$B63&$D$26:$D63,H$26:H63),"")} | H23: {=IFERROR(XLOOKUP($B$7&$C23,$B$26:$B63&$D$26:$D63,I$26:I63),"")} | I23: {=IFERROR(XLOOKUP($B$7&$C23,$B$26:$B63&$D$26:$D63,J$26:J63),"")} | J23: {=IFERROR(XLOOKUP($B$7&$C23,$B$26:$B63&$D$26:$D63,K$26:K63),"")} | K23: {=IFERROR(XLOOKUP($B$7&$C23,$B$26:$B63&$D$26:$D63,L$26:L63),"")} | ... Q23: {=IFERROR(XLOOKUP($B$7&$C23,$B$26:$B63&$D$26:$D63,R$26:R63),"")}
A24: =$B$7 -> 2024 | B24: 12 | C24: =DATE(A24,B24,1) -> 45627 | D24: {=IFERROR(XLOOKUP($B$7&$C24,$B$26:$B63&$D$26:$D63,E$26:E63),"")} | E24: {=IFERROR(XLOOKUP($B$7&$C24,$B$26:$B63&$D$26:$D63,F$26:F63),"")} | F24: {=IFERROR(XLOOKUP($B$7&$C24,$B$26:$B63&$D$26:$D63,G$26:G63),"")} | G24: {=IFERROR(XLOOKUP($B$7&$C24,$B$26:$B63&$D$26:$D63,H$26:H63),"")} | H24: {=IFERROR(XLOOKUP($B$7&$C24,$B$26:$B63&$D$26:$D63,I$26:I63),"")} | I24: {=IFERROR(XLOOKUP($B$7&$C24,$B$26:$B63&$D$26:$D63,J$26:J63),"")} | J24: {=IFERROR(XLOOKUP($B$7&$C24,$B$26:$B63&$D$26:$D63,K$26:K63),"")} | K24: {=IFERROR(XLOOKUP($B$7&$C24,$B$26:$B63&$D$26:$D63,L$26:L63),"")} | ... Q24: {=IFERROR(XLOOKUP($B$7&$C24,$B$26:$B63&$D$26:$D63,R$26:R63),"")}
B26: Ano | C26: Mês | D26: Ano e Mês | E26: Entrada | F26: Saída | G26: Lucro Líquido | H26: Fluxo de Caixa Acumulado | I26: Custos Fixos | J26: Custos Variáveis | K26: Despesas | L26: Investimentos | M26: Inadimplência | N26: Runway | O26: Margem de Contribuição | P26: Breakeven | Q26: Margem Líquida | R26: Faturamento
A27: -
B28: 2024 | C28: 1 | D28: =DATE(B28,C28,1) -> 45292 | E28: =SUMIFS('Base de Dados'!$M$6:$M63,'Base de Dados'!$O$6:$O63,MONTH(D28),'Base de Dados'!$P$6:$P63,YEAR(D28),'Base de Dados'!$E$6:$E63,$E$26,'Base de Dados'!$C$6:$C63,"Sim") -> #N/A | F28: =SUMIFS('Base de Dados'!$M$6:$M63,'Base de Dados'!$O$6:$O63,MONTH(D28),'Base de Dados'!$P$6:$P63,YEAR(D28),'Base de Dados'!$E$6:$E63,$F$26,'Base de Dados'!$C$6:$C63,"Sim") -> #N/A | G28: =E28-F28 -> #N/A | H28: =H27+G28 -> #N/A | I28: =SUMIFS('Base de Dados'!$M$6:$M63,'Base de Dados'!$O$6:$O63,MONTH(D28),'Base de Dados'!$P$6:$P63,YEAR(D28),'Base de Dados'!$F$6:$F63,$I$26,'Base de Dados'!$C$6:$C63,"Sim") -> #N/A | J28: =SUMIFS('Base de Dados'!$M$6:$M63,'Base de Dados'!$O$6:$O63,MONTH(D28),'Base de Dados'!$P$6:$P63,YEAR(D28),'Base de Dados'!$F$6:$F63,$J$26,'Base de Dados'!$C$6:$C63,"Sim") -> #N/A | K28: =SUMIFS('Base de Dados'!$M$6:$M63,'Base de Dados'!$O$6:$O63,MONTH(D28),'Base de Dados'!$P$6:$P63,YEAR(D28),'Base de Dados'!$F$6:$F63,$K$26,'Base de Dados'!$C$6:$C63,"Sim") -> #N/A | L28: =SUMIFS('Base de Dados'!$M$6:$M63,'Base de Dados'!$O$6:$O63,MONTH(D28),'Base de Dados'!$P$6:$P63,YEAR(D28),'Base de Dados'!$F$6:$F63,$L$26,'Base de Dados'!$C$6:$C63,"Sim") -> #N/A | M28: =SUMIFS('Base de Dados'!$M$6:$M63,'Base de Dados'!$O$6:$O63,MONTH(D28),'Base de Dados'!$P$6:$P63,YEAR(D28),'Base de Dados'!$E$6:$E63,$E$26,'Base de Dados'!$C$6:$C63,"Não") -> #N/A | N28: =IFERROR(H28/P28,0) -> 0 | O28: =IFERROR((E28-J28)/E28,0) -> 0 | P28: =IFERROR(I28/O28,0) -> 0 | Q28: =IFERROR(G28/E28,0) -> 0 | R28: =SUMIFS('Base de Dados'!$M$6:$M63,'Base de Dados'!$O$6:$O63,MONTH(D28),'Base de Dados'!$P$6:$P63,YEAR(D28),'Base de Dados'!$E$6:$E63,$E$26) -> #N/A
B29: 2024 | C29: 2 | D29: =DATE(B29,C29,1) -> 45323 | E29: =SUMIFS('Base de Dados'!$M$6:$M64,'Base de Dados'!$O$6:$O64,MONTH(D29),'Base de Dados'!$P$6:$P64,YEAR(D29),'Base de Dados'!$E$6:$E64,$E$26,'Base de Dados'!$C$6:$C64,"Sim") -> #N/A | F29: =SUMIFS('Base de Dados'!$M$6:$M64,'Base de Dados'!$O$6:$O64,MONTH(D29),'Base de Dados'!$P$6:$P64,YEAR(D29),'Base de Dados'!$E$6:$E64,$F$26,'Base de Dados'!$C$6:$C64,"Sim") -> #N/A | G29: =E29-F29 -> #N/A | H29: =H28+G29 -> #N/A | I29: =SUMIFS('Base de Dados'!$M$6:$M64,'Base de Dados'!$O$6:$O64,MONTH(D29),'Base de Dados'!$P$6:$P64,YEAR(D29),'Base de Dados'!$F$6:$F64,$I$26,'Base de Dados'!$C$6:$C64,"Sim") -> #N/A | J29: =SUMIFS('Base de Dados'!$M$6:$M64,'Base de Dados'!$O$6:$O64,MONTH(D29),'Base de Dados'!$P$6:$P64,YEAR(D29),'Base de Dados'!$F$6:$F64,$J$26,'Base de Dados'!$C$6:$C64,"Sim") -> #N/A | K29: =SUMIFS('Base de Dados'!$M$6:$M64,'Base de Dados'!$O$6:$O64,MONTH(D29),'Base de Dados'!$P$6:$P64,YEAR(D29),'Base de Dados'!$F$6:$F64,$K$26,'Base de Dados'!$C$6:$C64,"Sim") -> #N/A | L29: =SUMIFS('Base de Dados'!$M$6:$M64,'Base de Dados'!$O$6:$O64,MONTH(D29),'Base de Dados'!$P$6:$P64,YEAR(D29),'Base de Dados'!$F$6:$F64,$L$26,'Base de Dados'!$C$6:$C64,"Sim") -> #N/A | M29: =SUMIFS('Base de Dados'!$M$6:$M64,'Base de Dados'!$O$6:$O64,MONTH(D29),'Base de Dados'!$P$6:$P64,YEAR(D29),'Base de Dados'!$E$6:$E64,$E$26,'Base de Dados'!$C$6:$C64,"Não") -> #N/A | N29: =IFERROR(H29/P29,0) -> 0 | O29: =IFERROR((E29-J29)/E29,0) -> 0 | P29: =IFERROR(I29/O29,0) -> 0 | Q29: =IFERROR(G29/E29,0) -> 0 | R29: =SUMIFS('Base de Dados'!$M$6:$M64,'Base de Dados'!$O$6:$O64,MONTH(D29),'Base de Dados'!$P$6:$P64,YEAR(D29),'Base de Dados'!$E$6:$E64,$E$26) -> #N/A
B30: 2024 | C30: 3 | D30: =DATE(B30,C30,1) -> 45352 | E30: =SUMIFS('Base de Dados'!$M$6:$M65,'Base de Dados'!$O$6:$O65,MONTH(D30),'Base de Dados'!$P$6:$P65,YEAR(D30),'Base de Dados'!$E$6:$E65,$E$26,'Base de Dados'!$C$6:$C65,"Sim") -> #N/A | F30: =SUMIFS('Base de Dados'!$M$6:$M65,'Base de Dados'!$O$6:$O65,MONTH(D30),'Base de Dados'!$P$6:$P65,YEAR(D30),'Base de Dados'!$E$6:$E65,$F$26,'Base de Dados'!$C$6:$C65,"Sim") -> #N/A | G30: =E30-F30 -> #N/A | H30: =H29+G30 -> #N/A | I30: =SUMIFS('Base de Dados'!$M$6:$M65,'Base de Dados'!$O$6:$O65,MONTH(D30),'Base de Dados'!$P$6:$P65,YEAR(D30),'Base de Dados'!$F$6:$F65,$I$26,'Base de Dados'!$C$6:$C65,"Sim") -> #N/A | J30: =SUMIFS('Base de Dados'!$M$6:$M65,'Base de Dados'!$O$6:$O65,MONTH(D30),'Base de Dados'!$P$6:$P65,YEAR(D30),'Base de Dados'!$F$6:$F65,$J$26,'Base de Dados'!$C$6:$C65,"Sim") -> #N/A | K30: =SUMIFS('Base de Dados'!$M$6:$M65,'Base de Dados'!$O$6:$O65,MONTH(D30),'Base de Dados'!$P$6:$P65,YEAR(D30),'Base de Dados'!$F$6:$F65,$K$26,'Base de Dados'!$C$6:$C65,"Sim") -> #N/A | L30: =SUMIFS('Base de Dados'!$M$6:$M65,'Base de Dados'!$O$6:$O65,MONTH(D30),'Base de Dados'!$P$6:$P65,YEAR(D30),'Base de Dados'!$F$6:$F65,$L$26,'Base de Dados'!$C$6:$C65,"Sim") -> #N/A | M30: =SUMIFS('Base de Dados'!$M$6:$M65,'Base de Dados'!$O$6:$O65,MONTH(D30),'Base de Dados'!$P$6:$P65,YEAR(D30),'Base de Dados'!$E$6:$E65,$E$26,'Base de Dados'!$C$6:$C65,"Não") -> #N/A | N30: =IFERROR(H30/P30,0) -> 0 | O30: =IFERROR((E30-J30)/E30,0) -> 0 | P30: =IFERROR(I30/O30,0) -> 0 | Q30: =IFERROR(G30/E30,0) -> 0 | R30: =SUMIFS('Base de Dados'!$M$6:$M65,'Base de Dados'!$O$6:$O65,MONTH(D30),'Base de Dados'!$P$6:$P65,YEAR(D30),'Base de Dados'!$E$6:$E65,$E$26) -> #N/A
B31: 2024 | C31: 4 | D31: =DATE(B31,C31,1) -> 45383 | E31: =SUMIFS('Base de Dados'!$M$6:$M66,'Base de Dados'!$O$6:$O66,MONTH(D31),'Base de Dados'!$P$6:$P66,YEAR(D31),'Base de Dados'!$E$6:$E66,$E$26,'Base de Dados'!$C$6:$C66,"Sim") -> #N/A | F31: =SUMIFS('Base de Dados'!$M$6:$M66,'Base de Dados'!$O$6:$O66,MONTH(D31),'Base de Dados'!$P$6:$P66,YEAR(D31),'Base de Dados'!$E$6:$E66,$F$26,'Base de Dados'!$C$6:$C66,"Sim") -> #N/A | G31: =E31-F31 -> #N/A | H31: =H30+G31 -> #N/A | I31: =SUMIFS('Base de Dados'!$M$6:$M66,'Base de Dados'!$O$6:$O66,MONTH(D31),'Base de Dados'!$P$6:$P66,YEAR(D31),'Base de Dados'!$F$6:$F66,$I$26,'Base de Dados'!$C$6:$C66,"Sim") -> #N/A | J31: =SUMIFS('Base de Dados'!$M$6:$M66,'Base de Dados'!$O$6:$O66,MONTH(D31),'Base de Dados'!$P$6:$P66,YEAR(D31),'Base de Dados'!$F$6:$F66,$J$26,'Base de Dados'!$C$6:$C66,"Sim") -> #N/A | K31: =SUMIFS('Base de Dados'!$M$6:$M66,'Base de Dados'!$O$6:$O66,MONTH(D31),'Base de Dados'!$P$6:$P66,YEAR(D31),'Base de Dados'!$F$6:$F66,$K$26,'Base de Dados'!$C$6:$C66,"Sim") -> #N/A | L31: =SUMIFS('Base de Dados'!$M$6:$M66,'Base de Dados'!$O$6:$O66,MONTH(D31),'Base de Dados'!$P$6:$P66,YEAR(D31),'Base de Dados'!$F$6:$F66,$L$26,'Base de Dados'!$C$6:$C66,"Sim") -> #N/A | M31: =SUMIFS('Base de Dados'!$M$6:$M66,'Base de Dados'!$O$6:$O66,MONTH(D31),'Base de Dados'!$P$6:$P66,YEAR(D31),'Base de Dados'!$E$6:$E66,$E$26,'Base de Dados'!$C$6:$C66,"Não") -> #N/A | N31: =IFERROR(H31/P31,0) -> 0 | O31: =IFERROR((E31-J31)/E31,0) -> 0 | P31: =IFERROR(I31/O31,0) -> 0 | Q31: =IFERROR(G31/E31,0) -> 0 | R31: =SUMIFS('Base de Dados'!$M$6:$M66,'Base de Dados'!$O$6:$O66,MONTH(D31),'Base de Dados'!$P$6:$P66,YEAR(D31),'Base de Dados'!$E$6:$E66,$E$26) -> #N/A
B32: 2024 | C32: 5 | D32: =DATE(B32,C32,1) -> 45413 | E32: =SUMIFS('Base de Dados'!$M$6:$M67,'Base de Dados'!$O$6:$O67,MONTH(D32),'Base de Dados'!$P$6:$P67,YEAR(D32),'Base de Dados'!$E$6:$E67,$E$26,'Base de Dados'!$C$6:$C67,"Sim") -> #N/A | F32: =SUMIFS('Base de Dados'!$M$6:$M67,'Base de Dados'!$O$6:$O67,MONTH(D32),'Base de Dados'!$P$6:$P67,YEAR(D32),'Base de Dados'!$E$6:$E67,$F$26,'Base de Dados'!$C$6:$C67,"Sim") -> #N/A | G32: =E32-F32 -> #N/A | H32: =H31+G32 -> #N/A | I32: =SUMIFS('Base de Dados'!$M$6:$M67,'Base de Dados'!$O$6:$O67,MONTH(D32),'Base de Dados'!$P$6:$P67,YEAR(D32),'Base de Dados'!$F$6:$F67,$I$26,'Base de Dados'!$C$6:$C67,"Sim") -> #N/A | J32: =SUMIFS('Base de Dados'!$M$6:$M67,'Base de Dados'!$O$6:$O67,MONTH(D32),'Base de Dados'!$P$6:$P67,YEAR(D32),'Base de Dados'!$F$6:$F67,$J$26,'Base de Dados'!$C$6:$C67,"Sim") -> #N/A | K32: =SUMIFS('Base de Dados'!$M$6:$M67,'Base de Dados'!$O$6:$O67,MONTH(D32),'Base de Dados'!$P$6:$P67,YEAR(D32),'Base de Dados'!$F$6:$F67,$K$26,'Base de Dados'!$C$6:$C67,"Sim") -> #N/A | L32: =SUMIFS('Base de Dados'!$M$6:$M67,'Base de Dados'!$O$6:$O67,MONTH(D32),'Base de Dados'!$P$6:$P67,YEAR(D32),'Base de Dados'!$F$6:$F67,$L$26,'Base de Dados'!$C$6:$C67,"Sim") -> #N/A | M32: =SUMIFS('Base de Dados'!$M$6:$M67,'Base de Dados'!$O$6:$O67,MONTH(D32),'Base de Dados'!$P$6:$P67,YEAR(D32),'Base de Dados'!$E$6:$E67,$E$26,'Base de Dados'!$C$6:$C67,"Não") -> #N/A | N32: =IFERROR(H32/P32,0) -> 0 | O32: =IFERROR((E32-J32)/E32,0) -> 0 | P32: =IFERROR(I32/O32,0) -> 0 | Q32: =IFERROR(G32/E32,0) -> 0 | R32: =SUMIFS('Base de Dados'!$M$6:$M67,'Base de Dados'!$O$6:$O67,MONTH(D32),'Base de Dados'!$P$6:$P67,YEAR(D32),'Base de Dados'!$E$6:$E67,$E$26) -> #N/A
B33: 2024 | C33: 6 | D33: =DATE(B33,C33,1) -> 45444 | E33: =SUMIFS('Base de Dados'!$M$6:$M68,'Base de Dados'!$O$6:$O68,MONTH(D33),'Base de Dados'!$P$6:$P68,YEAR(D33),'Base de Dados'!$E$6:$E68,$E$26,'Base de Dados'!$C$6:$C68,"Sim") -> #N/A | F33: =SUMIFS('Base de Dados'!$M$6:$M68,'Base de Dados'!$O$6:$O68,MONTH(D33),'Base de Dados'!$P$6:$P68,YEAR(D33),'Base de Dados'!$E$6:$E68,$F$26,'Base de Dados'!$C$6:$C68,"Sim") -> #N/A | G33: =E33-F33 -> #N/A | H33: =H32+G33 -> #N/A | I33: =SUMIFS('Base de Dados'!$M$6:$M68,'Base de Dados'!$O$6:$O68,MONTH(D33),'Base de Dados'!$P$6:$P68,YEAR(D33),'Base de Dados'!$F$6:$F68,$I$26,'Base de Dados'!$C$6:$C68,"Sim") -> #N/A | J33: =SUMIFS('Base de Dados'!$M$6:$M68,'Base de Dados'!$O$6:$O68,MONTH(D33),'Base de Dados'!$P$6:$P68,YEAR(D33),'Base de Dados'!$F$6:$F68,$J$26,'Base de Dados'!$C$6:$C68,"Sim") -> #N/A | K33: =SUMIFS('Base de Dados'!$M$6:$M68,'Base de Dados'!$O$6:$O68,MONTH(D33),'Base de Dados'!$P$6:$P68,YEAR(D33),'Base de Dados'!$F$6:$F68,$K$26,'Base de Dados'!$C$6:$C68,"Sim") -> #N/A | L33: =SUMIFS('Base de Dados'!$M$6:$M68,'Base de Dados'!$O$6:$O68,MONTH(D33),'Base de Dados'!$P$6:$P68,YEAR(D33),'Base de Dados'!$F$6:$F68,$L$26,'Base de Dados'!$C$6:$C68,"Sim") -> #N/A | M33: =SUMIFS('Base de Dados'!$M$6:$M68,'Base de Dados'!$O$6:$O68,MONTH(D33),'Base de Dados'!$P$6:$P68,YEAR(D33),'Base de Dados'!$E$6:$E68,$E$26,'Base de Dados'!$C$6:$C68,"Não") -> #N/A | N33: =IFERROR(H33/P33,0) -> 0 | O33: =IFERROR((E33-J33)/E33,0) -> 0 | P33: =IFERROR(I33/O33,0) -> 0 | Q33: =IFERROR(G33/E33,0) -> 0 | R33: =SUMIFS('Base de Dados'!$M$6:$M68,'Base de Dados'!$O$6:$O68,MONTH(D33),'Base de Dados'!$P$6:$P68,YEAR(D33),'Base de Dados'!$E$6:$E68,$E$26) -> #N/A
B34: 2024 | C34: 7 | D34: =DATE(B34,C34,1) -> 45474 | E34: =SUMIFS('Base de Dados'!$M$6:$M69,'Base de Dados'!$O$6:$O69,MONTH(D34),'Base de Dados'!$P$6:$P69,YEAR(D34),'Base de Dados'!$E$6:$E69,$E$26,'Base de Dados'!$C$6:$C69,"Sim") -> #N/A | F34: =SUMIFS('Base de Dados'!$M$6:$M69,'Base de Dados'!$O$6:$O69,MONTH(D34),'Base de Dados'!$P$6:$P69,YEAR(D34),'Base de Dados'!$E$6:$E69,$F$26,'Base de Dados'!$C$6:$C69,"Sim") -> #N/A | G34: =E34-F34 -> #N/A | H34: =H33+G34 -> #N/A | I34: =SUMIFS('Base de Dados'!$M$6:$M69,'Base de Dados'!$O$6:$O69,MONTH(D34),'Base de Dados'!$P$6:$P69,YEAR(D34),'Base de Dados'!$F$6:$F69,$I$26,'Base de Dados'!$C$6:$C69,"Sim") -> #N/A | J34: =SUMIFS('Base de Dados'!$M$6:$M69,'Base de Dados'!$O$6:$O69,MONTH(D34),'Base de Dados'!$P$6:$P69,YEAR(D34),'Base de Dados'!$F$6:$F69,$J$26,'Base de Dados'!$C$6:$C69,"Sim") -> #N/A | K34: =SUMIFS('Base de Dados'!$M$6:$M69,'Base de Dados'!$O$6:$O69,MONTH(D34),'Base de Dados'!$P$6:$P69,YEAR(D34),'Base de Dados'!$F$6:$F69,$K$26,'Base de Dados'!$C$6:$C69,"Sim") -> #N/A | L34: =SUMIFS('Base de Dados'!$M$6:$M69,'Base de Dados'!$O$6:$O69,MONTH(D34),'Base de Dados'!$P$6:$P69,YEAR(D34),'Base de Dados'!$F$6:$F69,$L$26,'Base de Dados'!$C$6:$C69,"Sim") -> #N/A | M34: =SUMIFS('Base de Dados'!$M$6:$M69,'Base de Dados'!$O$6:$O69,MONTH(D34),'Base de Dados'!$P$6:$P69,YEAR(D34),'Base de Dados'!$E$6:$E69,$E$26,'Base de Dados'!$C$6:$C69,"Não") -> #N/A | N34: =IFERROR(H34/P34,0) -> 0 | O34: =IFERROR((E34-J34)/E34,0) -> 0 | P34: =IFERROR(I34/O34,0) -> 0 | Q34: =IFERROR(G34/E34,0) -> 0 | R34: =SUMIFS('Base de Dados'!$M$6:$M69,'Base de Dados'!$O$6:$O69,MONTH(D34),'Base de Dados'!$P$6:$P69,YEAR(D34),'Base de Dados'!$E$6:$E69,$E$26) -> #N/A
B35: 2024 | C35: 8 | D35: =DATE(B35,C35,1) -> 45505 | E35: =SUMIFS('Base de Dados'!$M$6:$M70,'Base de Dados'!$O$6:$O70,MONTH(D35),'Base de Dados'!$P$6:$P70,YEAR(D35),'Base de Dados'!$E$6:$E70,$E$26,'Base de Dados'!$C$6:$C70,"Sim") -> #N/A | F35: =SUMIFS('Base de Dados'!$M$6:$M70,'Base de Dados'!$O$6:$O70,MONTH(D35),'Base de Dados'!$P$6:$P70,YEAR(D35),'Base de Dados'!$E$6:$E70,$F$26,'Base de Dados'!$C$6:$C70,"Sim") -> #N/A | G35: =E35-F35 -> #N/A | H35: =H34+G35 -> #N/A | I35: =SUMIFS('Base de Dados'!$M$6:$M70,'Base de Dados'!$O$6:$O70,MONTH(D35),'Base de Dados'!$P$6:$P70,YEAR(D35),'Base de Dados'!$F$6:$F70,$I$26,'Base de Dados'!$C$6:$C70,"Sim") -> #N/A | J35: =SUMIFS('Base de Dados'!$M$6:$M70,'Base de Dados'!$O$6:$O70,MONTH(D35),'Base de Dados'!$P$6:$P70,YEAR(D35),'Base de Dados'!$F$6:$F70,$J$26,'Base de Dados'!$C$6:$C70,"Sim") -> #N/A | K35: =SUMIFS('Base de Dados'!$M$6:$M70,'Base de Dados'!$O$6:$O70,MONTH(D35),'Base de Dados'!$P$6:$P70,YEAR(D35),'Base de Dados'!$F$6:$F70,$K$26,'Base de Dados'!$C$6:$C70,"Sim") -> #N/A | L35: =SUMIFS('Base de Dados'!$M$6:$M70,'Base de Dados'!$O$6:$O70,MONTH(D35),'Base de Dados'!$P$6:$P70,YEAR(D35),'Base de Dados'!$F$6:$F70,$L$26,'Base de Dados'!$C$6:$C70,"Sim") -> #N/A | M35: =SUMIFS('Base de Dados'!$M$6:$M70,'Base de Dados'!$O$6:$O70,MONTH(D35),'Base de Dados'!$P$6:$P70,YEAR(D35),'Base de Dados'!$E$6:$E70,$E$26,'Base de Dados'!$C$6:$C70,"Não") -> #N/A | N35: =IFERROR(H35/P35,0) -> 0 | O35: =IFERROR((E35-J35)/E35,0) -> 0 | P35: =IFERROR(I35/O35,0) -> 0 | Q35: =IFERROR(G35/E35,0) -> 0 | R35: =SUMIFS('Base de Dados'!$M$6:$M70,'Base de Dados'!$O$6:$O70,MONTH(D35),'Base de Dados'!$P$6:$P70,YEAR(D35),'Base de Dados'!$E$6:$E70,$E$26) -> #N/A
B36: 2024 | C36: 9 | D36: =DATE(B36,C36,1) -> 45536 | E36: =SUMIFS('Base de Dados'!$M$6:$M71,'Base de Dados'!$O$6:$O71,MONTH(D36),'Base de Dados'!$P$6:$P71,YEAR(D36),'Base de Dados'!$E$6:$E71,$E$26,'Base de Dados'!$C$6:$C71,"Sim") -> #N/A | F36: =SUMIFS('Base de Dados'!$M$6:$M71,'Base de Dados'!$O$6:$O71,MONTH(D36),'Base de Dados'!$P$6:$P71,YEAR(D36),'Base de Dados'!$E$6:$E71,$F$26,'Base de Dados'!$C$6:$C71,"Sim") -> #N/A | G36: =E36-F36 -> #N/A | H36: =H35+G36 -> #N/A | I36: =SUMIFS('Base de Dados'!$M$6:$M71,'Base de Dados'!$O$6:$O71,MONTH(D36),'Base de Dados'!$P$6:$P71,YEAR(D36),'Base de Dados'!$F$6:$F71,$I$26,'Base de Dados'!$C$6:$C71,"Sim") -> #N/A | J36: =SUMIFS('Base de Dados'!$M$6:$M71,'Base de Dados'!$O$6:$O71,MONTH(D36),'Base de Dados'!$P$6:$P71,YEAR(D36),'Base de Dados'!$F$6:$F71,$J$26,'Base de Dados'!$C$6:$C71,"Sim") -> #N/A | K36: =SUMIFS('Base de Dados'!$M$6:$M71,'Base de Dados'!$O$6:$O71,MONTH(D36),'Base de Dados'!$P$6:$P71,YEAR(D36),'Base de Dados'!$F$6:$F71,$K$26,'Base de Dados'!$C$6:$C71,"Sim") -> #N/A | L36: =SUMIFS('Base de Dados'!$M$6:$M71,'Base de Dados'!$O$6:$O71,MONTH(D36),'Base de Dados'!$P$6:$P71,YEAR(D36),'Base de Dados'!$F$6:$F71,$L$26,'Base de Dados'!$C$6:$C71,"Sim") -> #N/A | M36: =SUMIFS('Base de Dados'!$M$6:$M71,'Base de Dados'!$O$6:$O71,MONTH(D36),'Base de Dados'!$P$6:$P71,YEAR(D36),'Base de Dados'!$E$6:$E71,$E$26,'Base de Dados'!$C$6:$C71,"Não") -> #N/A | N36: =IFERROR(H36/P36,0) -> 0 | O36: =IFERROR((E36-J36)/E36,0) -> 0 | P36: =IFERROR(I36/O36,0) -> 0 | Q36: =IFERROR(G36/E36,0) -> 0 | R36: =SUMIFS('Base de Dados'!$M$6:$M71,'Base de Dados'!$O$6:$O71,MONTH(D36),'Base de Dados'!$P$6:$P71,YEAR(D36),'Base de Dados'!$E$6:$E71,$E$26) -> #N/A
B37: 2024 | C37: 10 | D37: =DATE(B37,C37,1) -> 45566 | E37: =SUMIFS('Base de Dados'!$M$6:$M72,'Base de Dados'!$O$6:$O72,MONTH(D37),'Base de Dados'!$P$6:$P72,YEAR(D37),'Base de Dados'!$E$6:$E72,$E$26,'Base de Dados'!$C$6:$C72,"Sim") -> #N/A | F37: =SUMIFS('Base de Dados'!$M$6:$M72,'Base de Dados'!$O$6:$O72,MONTH(D37),'Base de Dados'!$P$6:$P72,YEAR(D37),'Base de Dados'!$E$6:$E72,$F$26,'Base de Dados'!$C$6:$C72,"Sim") -> #N/A | G37: =E37-F37 -> #N/A | H37: =H36+G37 -> #N/A | I37: =SUMIFS('Base de Dados'!$M$6:$M72,'Base de Dados'!$O$6:$O72,MONTH(D37),'Base de Dados'!$P$6:$P72,YEAR(D37),'Base de Dados'!$F$6:$F72,$I$26,'Base de Dados'!$C$6:$C72,"Sim") -> #N/A | J37: =SUMIFS('Base de Dados'!$M$6:$M72,'Base de Dados'!$O$6:$O72,MONTH(D37),'Base de Dados'!$P$6:$P72,YEAR(D37),'Base de Dados'!$F$6:$F72,$J$26,'Base de Dados'!$C$6:$C72,"Sim") -> #N/A | K37: =SUMIFS('Base de Dados'!$M$6:$M72,'Base de Dados'!$O$6:$O72,MONTH(D37),'Base de Dados'!$P$6:$P72,YEAR(D37),'Base de Dados'!$F$6:$F72,$K$26,'Base de Dados'!$C$6:$C72,"Sim") -> #N/A | L37: =SUMIFS('Base de Dados'!$M$6:$M72,'Base de Dados'!$O$6:$O72,MONTH(D37),'Base de Dados'!$P$6:$P72,YEAR(D37),'Base de Dados'!$F$6:$F72,$L$26,'Base de Dados'!$C$6:$C72,"Sim") -> #N/A | M37: =SUMIFS('Base de Dados'!$M$6:$M72,'Base de Dados'!$O$6:$O72,MONTH(D37),'Base de Dados'!$P$6:$P72,YEAR(D37),'Base de Dados'!$E$6:$E72,$E$26,'Base de Dados'!$C$6:$C72,"Não") -> #N/A | N37: =IFERROR(H37/P37,0) -> 0 | O37: =IFERROR((E37-J37)/E37,0) -> 0 | P37: =IFERROR(I37/O37,0) -> 0 | Q37: =IFERROR(G37/E37,0) -> 0 | R37: =SUMIFS('Base de Dados'!$M$6:$M72,'Base de Dados'!$O$6:$O72,MONTH(D37),'Base de Dados'!$P$6:$P72,YEAR(D37),'Base de Dados'!$E$6:$E72,$E$26) -> #N/A
B38: 2024 | C38: 11 | D38: =DATE(B38,C38,1) -> 45597 | E38: =SUMIFS('Base de Dados'!$M$6:$M73,'Base de Dados'!$O$6:$O73,MONTH(D38),'Base de Dados'!$P$6:$P73,YEAR(D38),'Base de Dados'!$E$6:$E73,$E$26,'Base de Dados'!$C$6:$C73,"Sim") -> #N/A | F38: =SUMIFS('Base de Dados'!$M$6:$M73,'Base de Dados'!$O$6:$O73,MONTH(D38),'Base de Dados'!$P$6:$P73,YEAR(D38),'Base de Dados'!$E$6:$E73,$F$26,'Base de Dados'!$C$6:$C73,"Sim") -> #N/A | G38: =E38-F38 -> #N/A | H38: =H37+G38 -> #N/A | I38: =SUMIFS('Base de Dados'!$M$6:$M73,'Base de Dados'!$O$6:$O73,MONTH(D38),'Base de Dados'!$P$6:$P73,YEAR(D38),'Base de Dados'!$F$6:$F73,$I$26,'Base de Dados'!$C$6:$C73,"Sim") -> #N/A | J38: =SUMIFS('Base de Dados'!$M$6:$M73,'Base de Dados'!$O$6:$O73,MONTH(D38),'Base de Dados'!$P$6:$P73,YEAR(D38),'Base de Dados'!$F$6:$F73,$J$26,'Base de Dados'!$C$6:$C73,"Sim") -> #N/A | K38: =SUMIFS('Base de Dados'!$M$6:$M73,'Base de Dados'!$O$6:$O73,MONTH(D38),'Base de Dados'!$P$6:$P73,YEAR(D38),'Base de Dados'!$F$6:$F73,$K$26,'Base de Dados'!$C$6:$C73,"Sim") -> #N/A | L38: =SUMIFS('Base de Dados'!$M$6:$M73,'Base de Dados'!$O$6:$O73,MONTH(D38),'Base de Dados'!$P$6:$P73,YEAR(D38),'Base de Dados'!$F$6:$F73,$L$26,'Base de Dados'!$C$6:$C73,"Sim") -> #N/A | M38: =SUMIFS('Base de Dados'!$M$6:$M73,'Base de Dados'!$O$6:$O73,MONTH(D38),'Base de Dados'!$P$6:$P73,YEAR(D38),'Base de Dados'!$E$6:$E73,$E$26,'Base de Dados'!$C$6:$C73,"Não") -> #N/A | N38: =IFERROR(H38/P38,0) -> 0 | O38: =IFERROR((E38-J38)/E38,0) -> 0 | P38: =IFERROR(I38/O38,0) -> 0 | Q38: =IFERROR(G38/E38,0) -> 0 | R38: =SUMIFS('Base de Dados'!$M$6:$M73,'Base de Dados'!$O$6:$O73,MONTH(D38),'Base de Dados'!$P$6:$P73,YEAR(D38),'Base de Dados'!$E$6:$E73,$E$26) -> #N/A
B39: 2024 | C39: 12 | D39: =DATE(B39,C39,1) -> 45627 | E39: =SUMIFS('Base de Dados'!$M$6:$M74,'Base de Dados'!$O$6:$O74,MONTH(D39),'Base de Dados'!$P$6:$P74,YEAR(D39),'Base de Dados'!$E$6:$E74,$E$26,'Base de Dados'!$C$6:$C74,"Sim") -> #N/A | F39: =SUMIFS('Base de Dados'!$M$6:$M74,'Base de Dados'!$O$6:$O74,MONTH(D39),'Base de Dados'!$P$6:$P74,YEAR(D39),'Base de Dados'!$E$6:$E74,$F$26,'Base de Dados'!$C$6:$C74,"Sim") -> #N/A | G39: =E39-F39 -> #N/A | H39: =H38+G39 -> #N/A | I39: =SUMIFS('Base de Dados'!$M$6:$M74,'Base de Dados'!$O$6:$O74,MONTH(D39),'Base de Dados'!$P$6:$P74,YEAR(D39),'Base de Dados'!$F$6:$F74,$I$26,'Base de Dados'!$C$6:$C74,"Sim") -> #N/A | J39: =SUMIFS('Base de Dados'!$M$6:$M74,'Base de Dados'!$O$6:$O74,MONTH(D39),'Base de Dados'!$P$6:$P74,YEAR(D39),'Base de Dados'!$F$6:$F74,$J$26,'Base de Dados'!$C$6:$C74,"Sim") -> #N/A | K39: =SUMIFS('Base de Dados'!$M$6:$M74,'Base de Dados'!$O$6:$O74,MONTH(D39),'Base de Dados'!$P$6:$P74,YEAR(D39),'Base de Dados'!$F$6:$F74,$K$26,'Base de Dados'!$C$6:$C74,"Sim") -> #N/A | L39: =SUMIFS('Base de Dados'!$M$6:$M74,'Base de Dados'!$O$6:$O74,MONTH(D39),'Base de Dados'!$P$6:$P74,YEAR(D39),'Base de Dados'!$F$6:$F74,$L$26,'Base de Dados'!$C$6:$C74,"Sim") -> #N/A | M39: =SUMIFS('Base de Dados'!$M$6:$M74,'Base de Dados'!$O$6:$O74,MONTH(D39),'Base de Dados'!$P$6:$P74,YEAR(D39),'Base de Dados'!$E$6:$E74,$E$26,'Base de Dados'!$C$6:$C74,"Não") -> #N/A | N39: =IFERROR(H39/P39,0) -> 0 | O39: =IFERROR((E39-J39)/E39,0) -> 0 | P39: =IFERROR(I39/O39,0) -> 0 | Q39: =IFERROR(G39/E39,0) -> 0 | R39: =SUMIFS('Base de Dados'!$M$6:$M74,'Base de Dados'!$O$6:$O74,MONTH(D39),'Base de Dados'!$P$6:$P74,YEAR(D39),'Base de Dados'!$E$6:$E74,$E$26) -> #N/A
... B63: 2026 | C63: 12 | D63: =DATE(B63,C63,1) -> 46357 | E63: =SUMIFS('Base de Dados'!$M$6:$M98,'Base de Dados'!$O$6:$O98,MONTH(D63),'Base de Dados'!$P$6:$P98,YEAR(D63),'Base de Dados'!$E$6:$E98,$E$26,'Base de Dados'!$C$6:$C98,"Sim") -> #N/A | F63: =SUMIFS('Base de Dados'!$M$6:$M98,'Base de Dados'!$O$6:$O98,MONTH(D63),'Base de Dados'!$P$6:$P98,YEAR(D63),'Base de Dados'!$E$6:$E98,$F$26,'Base de Dados'!$C$6:$C98,"Sim") -> #N/A | G63: =E63-F63 -> #N/A | H63: =H62+G63 -> #N/A | I63: =SUMIFS('Base de Dados'!$M$6:$M98,'Base de Dados'!$O$6:$O98,MONTH(D63),'Base de Dados'!$P$6:$P98,YEAR(D63),'Base de Dados'!$F$6:$F98,$I$26,'Base de Dados'!$C$6:$C98,"Sim") -> #N/A | J63: =SUMIFS('Base de Dados'!$M$6:$M98,'Base de Dados'!$O$6:$O98,MONTH(D63),'Base de Dados'!$P$6:$P98,YEAR(D63),'Base de Dados'!$F$6:$F98,$J$26,'Base de Dados'!$C$6:$C98,"Sim") -> #N/A | K63: =SUMIFS('Base de Dados'!$M$6:$M98,'Base de Dados'!$O$6:$O98,MONTH(D63),'Base de Dados'!$P$6:$P98,YEAR(D63),'Base de Dados'!$F$6:$F98,$K$26,'Base de Dados'!$C$6:$C98,"Sim") -> #N/A | L63: =SUMIFS('Base de Dados'!$M$6:$M98,'Base de Dados'!$O$6:$O98,MONTH(D63),'Base de Dados'!$P$6:$P98,YEAR(D63),'Base de Dados'!$F$6:$F98,$L$26,'Base de Dados'!$C$6:$C98,"Sim") -> #N/A | M63: =SUMIFS('Base de Dados'!$M$6:$M98,'Base de Dados'!$O$6:$O98,MONTH(D63),'Base de Dados'!$P$6:$P98,YEAR(D63),'Base de Dados'!$E$6:$E98,$E$26,'Base de Dados'!$C$6:$C98,"Não") -> #N/A | N63: =IFERROR(H63/P63,0) -> 0 | O63: =IFERROR((E63-J63)/E63,0) -> 0 | P63: =IFERROR(I63/O63,0) -> 0 | Q63: =IFERROR(G63/E63,0) -> 0 | R63: =SUMIFS('Base de Dados'!$M$6:$M98,'Base de Dados'!$O$6:$O98,MONTH(D63),'Base de Dados'!$P$6:$P98,YEAR(D63),'Base de Dados'!$E$6:$E98,$E$26) -> #N/A
